[
  {
    "id": "v_fba37dc4",
    "word": "The toast of Paris",
    "translation": "el orgullo de París",
    "source_movie": "Ratatouille",
    "year_processed": "2024",
    "global_frequency": 1
  },
  {
    "id": "v_63108ac3",
    "word": "Dazzling ascent",
    "translation": "ascenso deslumbrante",
    "source_movie": "Ratatouille",
    "year_processed": "2024",
    "global_frequency": 1
  },
  {
    "id": "v_031d8e2a",
    "word": "Envious",
    "translation": "envidioso, celoso",
    "source_movie": "Ratatouille",
    "year_processed": "2024",
    "global_frequency": 2
  },
  {
    "id": "v_7e2d88e1",
    "word": "Vanilla bean",
    "translation": "vaina de vainilla",
    "source_movie": "Ratatouille",
    "year_processed": "2024",
    "global_frequency": 1
  },
  {
    "id": "v_8ba25370",
    "word": "Small twist of lemon",
    "translation": "un toque de limón",
    "source_movie": "Ratatouille",
    "year_processed": "2024",
    "global_frequency": 1
  },
  {
    "id": "v_547f079a",
    "word": "Poison checker",
    "translation": "comprobar de veneno",
    "source_movie": "Ratatouille",
    "year_processed": "2024",
    "global_frequency": 1
  },
  {
    "id": "v_dc1b0361",
    "word": "Godliness",
    "translation": "perfección",
    "source_movie": "Ratatouille",
    "year_processed": "2024",
    "global_frequency": 1
  },
  {
    "id": "v_17e1a728",
    "word": "You get picky",
    "translation": "te jueves quisquilloso",
    "source_movie": "Ratatouille",
    "year_processed": "2024",
    "global_frequency": 1
  },
  {
    "id": "v_abdfcd2e",
    "word": "Paws",
    "translation": "patas",
    "source_movie": "Ratatouille",
    "year_processed": "2024",
    "global_frequency": 1
  },
  {
    "id": "v_441b8dd5",
    "word": "A few drops",
    "translation": "un poquito",
    "source_movie": "Ratatouille",
    "year_processed": "2024",
    "global_frequency": 1
  },
  {
    "id": "v_816a9f80",
    "word": "Pile",
    "translation": "montón, pila",
    "source_movie": "Ratatouille",
    "year_processed": "2024",
    "global_frequency": 2
  },
  {
    "id": "v_fa8e0a50",
    "word": "Get the smoky flavor nice and even",
    "translation": "consigo que el sabor ahumado queda uniforme",
    "source_movie": "Ratatouille",
    "year_processed": "2024",
    "global_frequency": 1
  },
  {
    "id": "v_36f2aee5",
    "word": "y gradable",
    "translation": "No registrada",
    "source_movie": "Ratatouille",
    "year_processed": "2024",
    "global_frequency": 1
  },
  {
    "id": "v_91cdd505",
    "word": "Gustav swears at it",
    "translation": "Gustar se queja de ella",
    "source_movie": "Ratatouille",
    "year_processed": "2024",
    "global_frequency": 1
  },
  {
    "id": "v_163b509c",
    "word": "Take so long (verb)",
    "translation": "tardar mucho",
    "source_movie": "Ratatouille",
    "year_processed": "2024",
    "global_frequency": 1
  },
  {
    "id": "v_a3fe9dac",
    "word": "Faint",
    "translation": "débil",
    "source_movie": "Ratatouille",
    "year_processed": "2024",
    "global_frequency": 2
  },
  {
    "id": "v_93e50263",
    "word": "A scathing review",
    "translation": "una reseña demoledora",
    "source_movie": "Ratatouille",
    "year_processed": "2024",
    "global_frequency": 1
  },
  {
    "id": "v_82b1c24f",
    "word": "A severe blow",
    "translation": "un golpe duro",
    "source_movie": "Ratatouille",
    "year_processed": "2024",
    "global_frequency": 1
  },
  {
    "id": "v_a6c6e848",
    "word": "root music poco despots",
    "translation": "No registrada",
    "source_movie": "Ratatouille",
    "year_processed": "2024",
    "global_frequency": 1
  },
  {
    "id": "v_51a29a46",
    "word": "Let me through!",
    "translation": "¡Pésame pasar!",
    "source_movie": "Ratatouille",
    "year_processed": "2024",
    "global_frequency": 2
  },
  {
    "id": "v_da57a2f0",
    "word": "Push off",
    "translation": "largar de aquí",
    "source_movie": "Ratatouille",
    "year_processed": "2024",
    "global_frequency": 1
  },
  {
    "id": "v_fb020daa",
    "word": "Paddle (verb)",
    "translation": "remar",
    "source_movie": "Ratatouille",
    "year_processed": "2024",
    "global_frequency": 1
  },
  {
    "id": "v_5ee0d5af",
    "word": "Which way?",
    "translation": "¿Por donde?",
    "source_movie": "Ratatouille",
    "year_processed": "2024",
    "global_frequency": 1
  },
  {
    "id": "v_7b85a4b0",
    "word": "Mope (verb)",
    "translation": "deprimir",
    "source_movie": "Ratatouille",
    "year_processed": "2024",
    "global_frequency": 1
  },
  {
    "id": "v_dfb8e166",
    "word": "But that is no match for wishful thinking",
    "translation": "pero eso no se pues contra las ilusiones",
    "source_movie": "Ratatouille",
    "year_processed": "2024",
    "global_frequency": 1
  },
  {
    "id": "v_fefee59d",
    "word": "You don’t have the guts",
    "translation": "no tener las agalla",
    "source_movie": "Ratatouille",
    "year_processed": "2024",
    "global_frequency": 1
  },
  {
    "id": "v_b3159cd5",
    "word": "As though",
    "translation": "como si",
    "source_movie": "Ratatouille",
    "year_processed": "2024",
    "global_frequency": 2
  },
  {
    "id": "v_c001c4a4",
    "word": "Come around",
    "translation": "venir",
    "source_movie": "Ratatouille",
    "year_processed": "2024",
    "global_frequency": 3
  },
  {
    "id": "v_4ec93dc6",
    "word": "Steamed pike up",
    "translation": "lucio al vapor",
    "source_movie": "Ratatouille",
    "year_processed": "2024",
    "global_frequency": 1
  },
  {
    "id": "v_ee944904",
    "word": "Come up",
    "translation": "salir",
    "source_movie": "Ratatouille",
    "year_processed": "2024",
    "global_frequency": 3
  },
  {
    "id": "v_04a303fe",
    "word": "Rack of lamb",
    "translation": "costilla de cordero",
    "source_movie": "Ratatouille",
    "year_processed": "2024",
    "global_frequency": 1
  },
  {
    "id": "v_cbefdd37",
    "word": "Leeks",
    "translation": "puerro",
    "source_movie": "Ratatouille",
    "year_processed": "2024",
    "global_frequency": 1
  },
  {
    "id": "v_5d1c011a",
    "word": "Seared salmon",
    "translation": "salmón sellado",
    "source_movie": "Ratatouille",
    "year_processed": "2024",
    "global_frequency": 1
  },
  {
    "id": "v_238c465d",
    "word": "Open down low",
    "translation": "ley del puño de hierro",
    "source_movie": "Ratatouille",
    "year_processed": "2024",
    "global_frequency": 1
  },
  {
    "id": "v_0413cbb1",
    "word": "I’m getting buried here",
    "translation": "me esto merienda de aburrimiento aquí",
    "source_movie": "Ratatouille",
    "year_processed": "2024",
    "global_frequency": 1
  },
  {
    "id": "v_2cc05eb7",
    "word": "Old flame",
    "translation": "el antiguo amor",
    "source_movie": "Ratatouille",
    "year_processed": "2024",
    "global_frequency": 1
  },
  {
    "id": "v_3ee13e3e",
    "word": "Afterlife-wise",
    "translation": "en el más allá",
    "source_movie": "Ratatouille",
    "year_processed": "2024",
    "global_frequency": 1
  },
  {
    "id": "v_63b2042d",
    "word": "Garbage boy",
    "translation": "chico de la basura",
    "source_movie": "Ratatouille",
    "year_processed": "2024",
    "global_frequency": 1
  },
  {
    "id": "v_d0d6f0f0",
    "word": "Figment",
    "translation": "figuración, ilusión",
    "source_movie": "Ratatouille",
    "year_processed": "2024",
    "global_frequency": 2
  },
  {
    "id": "v_33ec6aad",
    "word": "Come down",
    "translation": "bajar, descender",
    "source_movie": "Ratatouille",
    "year_processed": "2024",
    "global_frequency": 5
  },
  {
    "id": "v_e515aca2",
    "word": "Fire (verb)",
    "translation": "prender fuego",
    "source_movie": "Ratatouille",
    "year_processed": "2024",
    "global_frequency": 1
  },
  {
    "id": "v_f682a08c",
    "word": "Gall",
    "translation": "malicia, amargura",
    "source_movie": "Ratatouille",
    "year_processed": "2024",
    "global_frequency": 1
  },
  {
    "id": "v_98bb5f55",
    "word": "I should have drawn and quartered",
    "translation": "te tenería que haber colgado y",
    "source_movie": "Ratatouille",
    "year_processed": "2024",
    "global_frequency": 1
  },
  {
    "id": "v_b11b7c13",
    "word": "descuartizado",
    "translation": "No registrada",
    "source_movie": "Ratatouille",
    "year_processed": "2024",
    "global_frequency": 1
  },
  {
    "id": "v_95eb90d9",
    "word": "Squeeze out",
    "translation": "exprimir",
    "source_movie": "Ratatouille",
    "year_processed": "2024",
    "global_frequency": 2
  },
  {
    "id": "v_ab6a8aac",
    "word": "Blather (verb)",
    "translation": "hablar, decir, balbucear (tontería)",
    "source_movie": "Ratatouille",
    "year_processed": "2024",
    "global_frequency": 1
  },
  {
    "id": "v_2577be93",
    "word": "Uphold (verb)",
    "translation": "cumplir, acatar",
    "source_movie": "Ratatouille",
    "year_processed": "2024",
    "global_frequency": 3
  },
  {
    "id": "v_e555df76",
    "word": "His most cherished belief",
    "translation": "su creencia más preciada",
    "source_movie": "Ratatouille",
    "year_processed": "2024",
    "global_frequency": 1
  },
  {
    "id": "v_a95a9f91",
    "word": "A bold risk",
    "translation": "un riesgo audaz",
    "source_movie": "Ratatouille",
    "year_processed": "2024",
    "global_frequency": 1
  },
  {
    "id": "v_1f2b6804",
    "word": "Sneaky",
    "translation": "astuto",
    "source_movie": "Ratatouille",
    "year_processed": "2024",
    "global_frequency": 3
  },
  {
    "id": "v_b4c8a706",
    "word": "Overreaching (adjective)",
    "translation": "exagerado",
    "source_movie": "Ratatouille",
    "year_processed": "2024",
    "global_frequency": 1
  },
  {
    "id": "v_b914acdf",
    "word": "Close down",
    "translation": "clausurar, cerrar",
    "source_movie": "Ratatouille",
    "year_processed": "2024",
    "global_frequency": 2
  },
  {
    "id": "v_f265a204",
    "word": "Our reputation is hanging by a thread",
    "translation": "nuestra reputación esta en juego",
    "source_movie": "Ratatouille",
    "year_processed": "2024",
    "global_frequency": 1
  },
  {
    "id": "v_477084b0",
    "word": "Get fancy",
    "translation": "poner elegante",
    "source_movie": "Ratatouille",
    "year_processed": "2024",
    "global_frequency": 1
  },
  {
    "id": "v_92fe030f",
    "word": "Flipping",
    "translation": "vuelta, volteo",
    "source_movie": "Ratatouille",
    "year_processed": "2024",
    "global_frequency": 1
  },
  {
    "id": "v_62692329",
    "word": "Nod (verb)",
    "translation": "asentir (con la cabeza)",
    "source_movie": "Ratatouille",
    "year_processed": "2024",
    "global_frequency": 1
  },
  {
    "id": "v_e856cde8",
    "word": "Heat (en terminus de hoar)",
    "translation": "calefacción, calor",
    "source_movie": "Ratatouille",
    "year_processed": "2024",
    "global_frequency": 1
  },
  {
    "id": "v_6a84a07e",
    "word": "Hit the road (verb)",
    "translation": "largar de aquí, pirrarse",
    "source_movie": "Ratatouille",
    "year_processed": "2024",
    "global_frequency": 1
  },
  {
    "id": "v_ec905ae9",
    "word": "Write off",
    "translation": "dar por perdido",
    "source_movie": "Ratatouille",
    "year_processed": "2024",
    "global_frequency": 1
  },
  {
    "id": "v_226680e4",
    "word": "A spicy yet subtle taste experience",
    "translation": "una experiencia de sabor picante pero sutil",
    "source_movie": "Ratatouille",
    "year_processed": "2024",
    "global_frequency": 1
  },
  {
    "id": "v_3a105ef5",
    "word": "Against all odds",
    "translation": "contra toda las probabilidad",
    "source_movie": "Ratatouille",
    "year_processed": "2024",
    "global_frequency": 1
  },
  {
    "id": "v_695f374d",
    "word": "Nip (verb)",
    "translation": "pellizcar",
    "source_movie": "Ratatouille",
    "year_processed": "2024",
    "global_frequency": 1
  },
  {
    "id": "v_7d669b22",
    "word": "No scampering and scurrying",
    "translation": "nada de correteo y alboroto",
    "source_movie": "Ratatouille",
    "year_processed": "2024",
    "global_frequency": 1
  },
  {
    "id": "v_9f115c76",
    "word": "Think out",
    "translation": "pensar con claridad",
    "source_movie": "Ratatouille",
    "year_processed": "2024",
    "global_frequency": 1
  },
  {
    "id": "v_443ee24c",
    "word": "Pull off",
    "translation": "lograr, llevar a cabo",
    "source_movie": "Ratatouille",
    "year_processed": "2024",
    "global_frequency": 3
  },
  {
    "id": "v_952a1e1e",
    "word": "Head shake",
    "translation": "gesto con la cabeza",
    "source_movie": "Ratatouille",
    "year_processed": "2024",
    "global_frequency": 1
  },
  {
    "id": "v_db6d389c",
    "word": "Hate cuisine",
    "translation": "alta cocina",
    "source_movie": "Ratatouille",
    "year_processed": "2024",
    "global_frequency": 1
  },
  {
    "id": "v_80289dfa",
    "word": "Corn dogs",
    "translation": "perro caliente empanado",
    "source_movie": "Ratatouille",
    "year_processed": "2024",
    "global_frequency": 2
  },
  {
    "id": "v_c56dad67",
    "word": "Sausages dipped in batter and deep fried",
    "translation": "salchicha bañada en masa y frita",
    "source_movie": "Ratatouille",
    "year_processed": "2024",
    "global_frequency": 1
  },
  {
    "id": "v_55707024",
    "word": "Whip up",
    "translation": "preparar rápido",
    "source_movie": "Ratatouille",
    "year_processed": "2024",
    "global_frequency": 4
  },
  {
    "id": "v_f0bc38d2",
    "word": "Overalls",
    "translation": "uniforme de che",
    "source_movie": "Ratatouille",
    "year_processed": "2024",
    "global_frequency": 1
  },
  {
    "id": "v_fb44be9c",
    "word": "Will (abusive a un documents)",
    "translation": "testamento",
    "source_movie": "Ratatouille",
    "year_processed": "2024",
    "global_frequency": 1
  },
  {
    "id": "v_e2cb891e",
    "word": "Heir",
    "translation": "heredero",
    "source_movie": "Ratatouille",
    "year_processed": "2024",
    "global_frequency": 1
  },
  {
    "id": "v_0ccec82d",
    "word": "Resemblance",
    "translation": "semejanza",
    "source_movie": "Ratatouille",
    "year_processed": "2024",
    "global_frequency": 2
  },
  {
    "id": "v_db9df2cb",
    "word": "What of the timing of all this?",
    "translation": "¿Y el momento de todo esto?",
    "source_movie": "Ratatouille",
    "year_processed": "2024",
    "global_frequency": 1
  },
  {
    "id": "v_7131a116",
    "word": "A little digging",
    "translation": "un poco de investigación",
    "source_movie": "Ratatouille",
    "year_processed": "2024",
    "global_frequency": 1
  },
  {
    "id": "v_85786eb7",
    "word": "Dinner rush",
    "translation": "hora de la cena",
    "source_movie": "Ratatouille",
    "year_processed": "2024",
    "global_frequency": 1
  },
  {
    "id": "v_983d241f",
    "word": "Keep your station clear!",
    "translation": "¡Mantón tu puesto despejado!",
    "source_movie": "Ratatouille",
    "year_processed": "2024",
    "global_frequency": 1
  },
  {
    "id": "v_1f4aca53",
    "word": "Pile up",
    "translation": "apilar, amontonar",
    "source_movie": "Ratatouille",
    "year_processed": "2024",
    "global_frequency": 1
  },
  {
    "id": "v_ee2d4e8c",
    "word": "Keep your hands and arms in",
    "translation": "mantón tus menos y brazo dentro",
    "source_movie": "Ratatouille",
    "year_processed": "2024",
    "global_frequency": 1
  },
  {
    "id": "v_255d7f82",
    "word": "Sharp (verb)",
    "translation": "afilar",
    "source_movie": "Ratatouille",
    "year_processed": "2024",
    "global_frequency": 1
  },
  {
    "id": "v_eff4f2a1",
    "word": "Messy apron",
    "translation": "delantal sucio",
    "source_movie": "Ratatouille",
    "year_processed": "2024",
    "global_frequency": 1
  },
  {
    "id": "v_1bce638f",
    "word": "Curst",
    "translation": "corteza (de un pan)",
    "source_movie": "Ratatouille",
    "year_processed": "2024",
    "global_frequency": 1
  },
  {
    "id": "v_65575641",
    "word": "Crackle",
    "translation": "crujido",
    "source_movie": "Ratatouille",
    "year_processed": "2024",
    "global_frequency": 1
  },
  {
    "id": "v_7a8fc3ae",
    "word": "Pick (substantive)",
    "translation": "elección",
    "source_movie": "Ratatouille",
    "year_processed": "2024",
    "global_frequency": 1
  },
  {
    "id": "v_7ac77d0c",
    "word": "Grower",
    "translation": "agricultor",
    "source_movie": "Ratatouille",
    "year_processed": "2024",
    "global_frequency": 1
  },
  {
    "id": "v_0ec1abab",
    "word": "Snooty",
    "translation": "presumido",
    "source_movie": "Ratatouille",
    "year_processed": "2024",
    "global_frequency": 2
  },
  {
    "id": "v_a9002157",
    "word": "Ringmaster",
    "translation": "director de circo",
    "source_movie": "Ratatouille",
    "year_processed": "2024",
    "global_frequency": 1
  },
  {
    "id": "v_b4cbd2cd",
    "word": "A ballpoint pen",
    "translation": "pluma, polígrafo, lapicero",
    "source_movie": "Ratatouille",
    "year_processed": "2024",
    "global_frequency": 1
  },
  {
    "id": "v_d1761e49",
    "word": "What are you blathering about?",
    "translation": "¿De que estas hablado?",
    "source_movie": "Ratatouille",
    "year_processed": "2024",
    "global_frequency": 1
  },
  {
    "id": "v_9b175ff0",
    "word": "Sweetbread",
    "translation": "molleja",
    "source_movie": "Ratatouille",
    "year_processed": "2024",
    "global_frequency": 1
  },
  {
    "id": "v_312e7723",
    "word": "Diners (en terminus de restaurants)",
    "translation": "comensal",
    "source_movie": "Ratatouille",
    "year_processed": "2024",
    "global_frequency": 1
  },
  {
    "id": "v_658257a2",
    "word": "A budding chef",
    "translation": "un che en viernes",
    "source_movie": "Ratatouille",
    "year_processed": "2024",
    "global_frequency": 1
  },
  {
    "id": "v_f4ce4c22",
    "word": "Seaweed salt crust",
    "translation": "costra de sal de alias",
    "source_movie": "Ratatouille",
    "year_processed": "2024",
    "global_frequency": 1
  },
  {
    "id": "v_4d608471",
    "word": "Cuttlefish tentacle",
    "translation": "tentáculo de calamar",
    "source_movie": "Ratatouille",
    "year_processed": "2024",
    "global_frequency": 1
  },
  {
    "id": "v_7183ffcd",
    "word": "Heyduck egg",
    "translation": "huevo de almeja",
    "source_movie": "Ratatouille",
    "year_processed": "2024",
    "global_frequency": 1
  },
  {
    "id": "v_11900426",
    "word": "White fungus",
    "translation": "hongo blanco",
    "source_movie": "Ratatouille",
    "year_processed": "2024",
    "global_frequency": 1
  },
  {
    "id": "v_a1d24aa6",
    "word": "Veal stomach",
    "translation": "callo de ternera",
    "source_movie": "Ratatouille",
    "year_processed": "2024",
    "global_frequency": 1
  },
  {
    "id": "v_3082ae16",
    "word": "Soak (verb)",
    "translation": "remojar",
    "source_movie": "Ratatouille",
    "year_processed": "2024",
    "global_frequency": 2
  },
  {
    "id": "v_886bc65c",
    "word": "Real quick",
    "translation": "muy rápido",
    "source_movie": "Ratatouille",
    "year_processed": "2024",
    "global_frequency": 2
  },
  {
    "id": "v_19b07c8f",
    "word": "Toque",
    "translation": "gorro de cocinero",
    "source_movie": "Ratatouille",
    "year_processed": "2024",
    "global_frequency": 1
  },
  {
    "id": "v_3968ec29",
    "word": "Toasting your success, eh, Linguini?",
    "translation": "¿Celebrador tu éxito, eh, Linguini?",
    "source_movie": "Ratatouille",
    "year_processed": "2024",
    "global_frequency": 1
  },
  {
    "id": "v_9d9f753f",
    "word": "Non-idiocy",
    "translation": "inteligencia",
    "source_movie": "Ratatouille",
    "year_processed": "2024",
    "global_frequency": 1
  },
  {
    "id": "v_fae19007",
    "word": "Rejectamenta",
    "translation": "basura, desecho",
    "source_movie": "Ratatouille",
    "year_processed": "2024",
    "global_frequency": 1
  },
  {
    "id": "v_b5217e68",
    "word": "Guinea pigs",
    "translation": "conejillo de india",
    "source_movie": "Ratatouille",
    "year_processed": "2024",
    "global_frequency": 2
  },
  {
    "id": "v_131195c2",
    "word": "Work down",
    "translation": "tragar",
    "source_movie": "Ratatouille",
    "year_processed": "2024",
    "global_frequency": 1
  },
  {
    "id": "v_3a749ff1",
    "word": "Chew (verb)",
    "translation": "masticar",
    "source_movie": "Ratatouille",
    "year_processed": "2024",
    "global_frequency": 3
  },
  {
    "id": "v_8fba8a9a",
    "word": "Okay nuttiness",
    "translation": "sabor a roble y nueve",
    "source_movie": "Ratatouille",
    "year_processed": "2024",
    "global_frequency": 1
  },
  {
    "id": "v_0273c743",
    "word": "Crisp",
    "translation": "crujiente",
    "source_movie": "Ratatouille",
    "year_processed": "2024",
    "global_frequency": 2
  },
  {
    "id": "v_f2a2875a",
    "word": "Slight tang on the finish",
    "translation": "un ligero toque ácido al final",
    "source_movie": "Ratatouille",
    "year_processed": "2024",
    "global_frequency": 1
  },
  {
    "id": "v_7d14f9c2",
    "word": "Everyone will be thrilled!",
    "translation": "¡Todo estar encantado!",
    "source_movie": "Ratatouille",
    "year_processed": "2024",
    "global_frequency": 1
  },
  {
    "id": "v_54c4d0b7",
    "word": "Squalor",
    "translation": "miseria",
    "source_movie": "Ratatouille",
    "year_processed": "2024",
    "global_frequency": 2
  },
  {
    "id": "v_1abdb4b6",
    "word": "Stew",
    "translation": "guiso",
    "source_movie": "Ratatouille",
    "year_processed": "2024",
    "global_frequency": 2
  },
  {
    "id": "v_1726906f",
    "word": "Regrettably we are all out of wine",
    "translation": "lamentablemente, se nos acabo el vino",
    "source_movie": "Ratatouille",
    "year_processed": "2024",
    "global_frequency": 1
  },
  {
    "id": "v_41b7c155",
    "word": "A surplus of snobbery",
    "translation": "un exceso de escotismo",
    "source_movie": "Ratatouille",
    "year_processed": "2024",
    "global_frequency": 1
  },
  {
    "id": "v_54815cad",
    "word": "A cold splash of reality",
    "translation": "un baño de realidad",
    "source_movie": "Ratatouille",
    "year_processed": "2024",
    "global_frequency": 1
  },
  {
    "id": "v_b0cbcc27",
    "word": "The band’s really on tonight",
    "translation": "la banda esta tocado increíblemente hoy",
    "source_movie": "Ratatouille",
    "year_processed": "2024",
    "global_frequency": 1
  },
  {
    "id": "v_0d60a741",
    "word": "A close-is sort of range",
    "translation": "más o menos cerca",
    "source_movie": "Ratatouille",
    "year_processed": "2024",
    "global_frequency": 1
  },
  {
    "id": "v_f6407fd4",
    "word": "Countertype",
    "translation": "encimera",
    "source_movie": "Ratatouille",
    "year_processed": "2024",
    "global_frequency": 1
  },
  {
    "id": "v_930dd42b",
    "word": "Intrude (verb)",
    "translation": "interrumpir, intrometerse",
    "source_movie": "Ratatouille",
    "year_processed": "2024",
    "global_frequency": 1
  },
  {
    "id": "v_9d586002",
    "word": "Dazzle (verb)",
    "translation": "deslumbrar",
    "source_movie": "Ratatouille",
    "year_processed": "2024",
    "global_frequency": 2
  },
  {
    "id": "v_5f4dca7d",
    "word": "And then you blow past me?",
    "translation": "¿Y me superar así sin más?",
    "source_movie": "Ratatouille",
    "year_processed": "2024",
    "global_frequency": 1
  },
  {
    "id": "v_a80102a0",
    "word": "Motorcycle away",
    "translation": "alejar en motocicleta",
    "source_movie": "Ratatouille",
    "year_processed": "2024",
    "global_frequency": 1
  },
  {
    "id": "v_21fa9ead",
    "word": "Rash",
    "translation": "sarpullido",
    "source_movie": "Ratatouille",
    "year_processed": "2024",
    "global_frequency": 5
  },
  {
    "id": "v_c521c039",
    "word": "Learner",
    "translation": "aprendiz",
    "source_movie": "Ratatouille",
    "year_processed": "2024",
    "global_frequency": 1
  },
  {
    "id": "v_75cab782",
    "word": "Microwave egg rolls",
    "translation": "pollito de primavera al microondas",
    "source_movie": "Ratatouille",
    "year_processed": "2024",
    "global_frequency": 1
  },
  {
    "id": "v_0e6e5fdf",
    "word": "Tourist trade",
    "translation": "industria turística",
    "source_movie": "Ratatouille",
    "year_processed": "2024",
    "global_frequency": 1
  },
  {
    "id": "v_29fe97b3",
    "word": "Rightful place",
    "translation": "lugar legítimo",
    "source_movie": "Ratatouille",
    "year_processed": "2024",
    "global_frequency": 1
  },
  {
    "id": "v_700a7ebb",
    "word": "Timing",
    "translation": "las cosa encajar a la perfección",
    "source_movie": "Ratatouille",
    "year_processed": "2024",
    "global_frequency": 2
  },
  {
    "id": "v_b4dbb7e4",
    "word": "The whole thing is a setup",
    "translation": "todo es una trampa",
    "source_movie": "Ratatouille",
    "year_processed": "2024",
    "global_frequency": 1
  },
  {
    "id": "v_842baa00",
    "word": "Toy (verb)",
    "translation": "jugar",
    "source_movie": "Ratatouille",
    "year_processed": "2024",
    "global_frequency": 1
  },
  {
    "id": "v_c082abe7",
    "word": "Taunting me with that rat",
    "translation": "provocándome con esa rata",
    "source_movie": "Ratatouille",
    "year_processed": "2024",
    "global_frequency": 1
  },
  {
    "id": "v_d57037b6",
    "word": "He’s consorting with it",
    "translation": "se esta juntador con él",
    "source_movie": "Ratatouille",
    "year_processed": "2024",
    "global_frequency": 1
  },
  {
    "id": "v_a99bad97",
    "word": "Theatricality",
    "translation": "teatralidad",
    "source_movie": "Ratatouille",
    "year_processed": "2024",
    "global_frequency": 1
  },
  {
    "id": "v_239bb252",
    "word": "Suck into",
    "translation": "absorber",
    "source_movie": "Ratatouille",
    "year_processed": "2024",
    "global_frequency": 1
  },
  {
    "id": "v_a381bfa7",
    "word": "Lovable",
    "translation": "adorable",
    "source_movie": "Ratatouille",
    "year_processed": "2024",
    "global_frequency": 1
  },
  {
    "id": "v_693272b0",
    "word": "Cease (verb)",
    "translation": "cesar, dejar de",
    "source_movie": "Ratatouille",
    "year_processed": "2024",
    "global_frequency": 1
  },
  {
    "id": "v_64a43ecb",
    "word": "I did’t think you meant them",
    "translation": "no pensar que lo tijera en serio",
    "source_movie": "Ratatouille",
    "year_processed": "2024",
    "global_frequency": 1
  },
  {
    "id": "v_b4860470",
    "word": "The food safe",
    "translation": "el frigorífico",
    "source_movie": "Ratatouille",
    "year_processed": "2024",
    "global_frequency": 1
  },
  {
    "id": "v_b1512cb0",
    "word": "Hawk (verb)",
    "translation": "vender (con agresividad)",
    "source_movie": "Ratatouille",
    "year_processed": "2024",
    "global_frequency": 3
  },
  {
    "id": "v_425bb07b",
    "word": "File (verb)",
    "translation": "archivar",
    "source_movie": "Ratatouille",
    "year_processed": "2024",
    "global_frequency": 1
  },
  {
    "id": "v_c886eeec",
    "word": "Bottoms up!",
    "translation": "¡Salud!",
    "source_movie": "Ratatouille",
    "year_processed": "2024",
    "global_frequency": 1
  },
  {
    "id": "v_3fee18a6",
    "word": "Rise (substantive)",
    "translation": "ascenso, crecimiento",
    "source_movie": "Ratatouille",
    "year_processed": "2024",
    "global_frequency": 2
  },
  {
    "id": "v_c8fa9f98",
    "word": "I’ll slot you in",
    "translation": "te incluir",
    "source_movie": "Ratatouille",
    "year_processed": "2024",
    "global_frequency": 1
  },
  {
    "id": "v_80f8dce9",
    "word": "Dearest",
    "translation": "querido(a)",
    "source_movie": "Ratatouille",
    "year_processed": "2024",
    "global_frequency": 1
  },
  {
    "id": "v_d917beae",
    "word": "Yank (verb)",
    "translation": "arrancar, arrastrar",
    "source_movie": "Ratatouille",
    "year_processed": "2024",
    "global_frequency": 1
  },
  {
    "id": "v_ab81fdd3",
    "word": "Cool off",
    "translation": "calmar",
    "source_movie": "Ratatouille",
    "year_processed": "2024",
    "global_frequency": 2
  },
  {
    "id": "v_8dec025f",
    "word": "Get your mind right",
    "translation": "enfocar tu cabeza",
    "source_movie": "Ratatouille",
    "year_processed": "2024",
    "global_frequency": 1
  },
  {
    "id": "v_35c49bf2",
    "word": "Fluffy bunny",
    "translation": "conejo adorable",
    "source_movie": "Ratatouille",
    "year_processed": "2024",
    "global_frequency": 1
  },
  {
    "id": "v_157f891d",
    "word": "An inside job",
    "translation": "un trabajo desde dentro",
    "source_movie": "Ratatouille",
    "year_processed": "2024",
    "global_frequency": 2
  },
  {
    "id": "v_f87d006b",
    "word": "I see the appeal",
    "translation": "entierro el atractivo",
    "source_movie": "Ratatouille",
    "year_processed": "2024",
    "global_frequency": 1
  },
  {
    "id": "v_633c952d",
    "word": "I’d like your heart roasted on a spit",
    "translation": "me gustar que tu corazón se asada en un",
    "source_movie": "Ratatouille",
    "year_processed": "2024",
    "global_frequency": 1
  },
  {
    "id": "v_bce8b7be",
    "word": "isador",
    "translation": "No registrada",
    "source_movie": "Ratatouille",
    "year_processed": "2024",
    "global_frequency": 1
  },
  {
    "id": "v_aa0bf0e9",
    "word": "Overheated puffery",
    "translation": "exageración excesiva",
    "source_movie": "Ratatouille",
    "year_processed": "2024",
    "global_frequency": 1
  },
  {
    "id": "v_f55d78d1",
    "word": "You know what I’m craving?",
    "translation": "¿Saber lo que se me apetecer?",
    "source_movie": "Ratatouille",
    "year_processed": "2024",
    "global_frequency": 1
  },
  {
    "id": "v_0ed75e38",
    "word": "Well seasoned perspective",
    "translation": "una perspectiva bien sazonada",
    "source_movie": "Ratatouille",
    "year_processed": "2024",
    "global_frequency": 1
  },
  {
    "id": "v_9311b490",
    "word": "Fresh out",
    "translation": "recién salido",
    "source_movie": "Ratatouille",
    "year_processed": "2024",
    "global_frequency": 1
  },
  {
    "id": "v_4f85ae88",
    "word": "Nicely",
    "translation": "agradablemente",
    "source_movie": "Ratatouille",
    "year_processed": "2024",
    "global_frequency": 1
  },
  {
    "id": "v_ae12b746",
    "word": "Tell him to hit me with his best shot",
    "translation": "dije que me tegue con su mejor tiro",
    "source_movie": "Ratatouille",
    "year_processed": "2024",
    "global_frequency": 1
  },
  {
    "id": "v_bbf07862",
    "word": "Cage",
    "translation": "jaula",
    "source_movie": "Ratatouille",
    "year_processed": "2024",
    "global_frequency": 3
  },
  {
    "id": "v_ecd5f27b",
    "word": "Await (verb)",
    "translation": "aguardar, acechar",
    "source_movie": "Ratatouille",
    "year_processed": "2024",
    "global_frequency": 3
  },
  {
    "id": "v_95344620",
    "word": "Halve",
    "translation": "mitad",
    "source_movie": "Ratatouille",
    "year_processed": "2024",
    "global_frequency": 1
  },
  {
    "id": "v_8c99b687",
    "word": "I’m talking about guts",
    "translation": "esto hablado sobre agalla",
    "source_movie": "Ratatouille",
    "year_processed": "2024",
    "global_frequency": 1
  },
  {
    "id": "v_794679f7",
    "word": "We’ll get it done",
    "translation": "lo lograremos",
    "source_movie": "Ratatouille",
    "year_processed": "2024",
    "global_frequency": 1
  },
  {
    "id": "v_3c242855",
    "word": "We’re a little short tonight",
    "translation": "estados un poco corto esta noche",
    "source_movie": "Ratatouille",
    "year_processed": "2024",
    "global_frequency": 1
  },
  {
    "id": "v_22a7402a",
    "word": "Tenderized",
    "translation": "ablandador, marginado",
    "source_movie": "Ratatouille",
    "year_processed": "2024",
    "global_frequency": 1
  },
  {
    "id": "v_33cb69f4",
    "word": "Stick and move",
    "translation": "muévanse con rapidez",
    "source_movie": "Ratatouille",
    "year_processed": "2024",
    "global_frequency": 2
  },
  {
    "id": "v_95b3cb46",
    "word": "Keep whisking",
    "translation": "sian batido",
    "source_movie": "Ratatouille",
    "year_processed": "2024",
    "global_frequency": 1
  },
  {
    "id": "v_2d4eb91c",
    "word": "Boil (verb)",
    "translation": "hervir",
    "source_movie": "Ratatouille",
    "year_processed": "2024",
    "global_frequency": 2
  },
  {
    "id": "v_00d543bb",
    "word": "Toughen (verb)",
    "translation": "endurecer",
    "source_movie": "Ratatouille",
    "year_processed": "2024",
    "global_frequency": 1
  },
  {
    "id": "v_03ce0ced",
    "word": "Pheasant",
    "translation": "faisán",
    "source_movie": "Ratatouille",
    "year_processed": "2024",
    "global_frequency": 1
  },
  {
    "id": "v_382cacdc",
    "word": "Peasant dish",
    "translation": "plato campesino",
    "source_movie": "Ratatouille",
    "year_processed": "2024",
    "global_frequency": 1
  },
  {
    "id": "v_16b1c027",
    "word": "So be it",
    "translation": "que así se",
    "source_movie": "Ratatouille",
    "year_processed": "2024",
    "global_frequency": 2
  },
  {
    "id": "v_69b3fbfd",
    "word": "Offer up",
    "translation": "ofrecer, consagrar",
    "source_movie": "Ratatouille",
    "year_processed": "2024",
    "global_frequency": 3
  },
  {
    "id": "v_8eff8598",
    "word": "And their selves",
    "translation": "y su persona",
    "source_movie": "Ratatouille",
    "year_processed": "2024",
    "global_frequency": 1
  },
  {
    "id": "v_240cba67",
    "word": "Thrive (verb)",
    "translation": "prosperar",
    "source_movie": "Ratatouille",
    "year_processed": "2024",
    "global_frequency": 2
  },
  {
    "id": "v_218cf68b",
    "word": "The bitter truth",
    "translation": "la dura realidad",
    "source_movie": "Ratatouille",
    "year_processed": "2024",
    "global_frequency": 1
  },
  {
    "id": "v_1fc3dfff",
    "word": "Unkind",
    "translation": "duro, desconsiderado",
    "source_movie": "Ratatouille",
    "year_processed": "2024",
    "global_frequency": 3
  },
  {
    "id": "v_3de24e3b",
    "word": "Preconceptions",
    "translation": "prejuicio",
    "source_movie": "Ratatouille",
    "year_processed": "2024",
    "global_frequency": 1
  },
  {
    "id": "v_e22445e2",
    "word": "A gross understatement",
    "translation": "una subestimación enorme",
    "source_movie": "Ratatouille",
    "year_processed": "2024",
    "global_frequency": 1
  },
  {
    "id": "v_b2cd7647",
    "word": "They have rocked me to my core",
    "translation": "me ha sacudido hasta la medula",
    "source_movie": "Ratatouille",
    "year_processed": "2024",
    "global_frequency": 1
  },
  {
    "id": "v_9fb27f32",
    "word": "The finest chef",
    "translation": "el mejor che",
    "source_movie": "Ratatouille",
    "year_processed": "2024",
    "global_frequency": 1
  },
  {
    "id": "v_1c95289f",
    "word": "Unpredictability",
    "translation": "imprevisibilidad",
    "source_movie": "Ratatouille",
    "year_processed": "2024",
    "global_frequency": 1
  },
  {
    "id": "v_1f6be0c8",
    "word": "They ratted us out",
    "translation": "nos delatar",
    "source_movie": "Ratatouille",
    "year_processed": "2024",
    "global_frequency": 1
  }
]