[
  {
    "id": "v_88738a82",
    "word": "Timer ticking",
    "translation": "temporizar en marcha",
    "source_movie": "Taylor Swift The Eras Tour Film",
    "year_processed": "2024",
    "global_frequency": 1
  },
  {
    "id": "v_81157c93",
    "word": "Soft gasp",
    "translation": "jadeo suave",
    "source_movie": "Taylor Swift The Eras Tour Film",
    "year_processed": "2024",
    "global_frequency": 1
  },
  {
    "id": "v_26b0ba23",
    "word": "Backup singers",
    "translation": "cantante de apoyo",
    "source_movie": "Taylor Swift The Eras Tour Film",
    "year_processed": "2024",
    "global_frequency": 1
  },
  {
    "id": "v_59ebbb25",
    "word": "The whole school is rolling fake dice",
    "translation": "toda la escuela esta tirado dado falso",
    "source_movie": "Taylor Swift The Eras Tour Film",
    "year_processed": "2024",
    "global_frequency": 1
  },
  {
    "id": "v_d6bc1692",
    "word": "The heartbreak prince",
    "translation": "el príncipe rompecorazones",
    "source_movie": "Taylor Swift The Eras Tour Film",
    "year_processed": "2024",
    "global_frequency": 1
  },
  {
    "id": "v_81941e74",
    "word": "Voted most likely to run away",
    "translation": "volado como el más propenso a huir/fugar/escañarse",
    "source_movie": "Taylor Swift The Eras Tour Film",
    "year_processed": "2024",
    "global_frequency": 1
  },
  {
    "id": "v_13bdd58d",
    "word": "Fever dream high",
    "translation": "sueño febril",
    "source_movie": "Taylor Swift The Eras Tour Film",
    "year_processed": "2024",
    "global_frequency": 1
  },
  {
    "id": "v_791d69b2",
    "word": "I caught it",
    "translation": "lo cotí, lo pillo",
    "source_movie": "Taylor Swift The Eras Tour Film",
    "year_processed": "2024",
    "global_frequency": 1
  },
  {
    "id": "v_e6a9d3f9",
    "word": "Be waiting below",
    "translation": "estar esperanto abajo",
    "source_movie": "Taylor Swift The Eras Tour Film",
    "year_processed": "2024",
    "global_frequency": 1
  },
  {
    "id": "v_a83091a4",
    "word": "Roll the dice",
    "translation": "tirar los dado",
    "source_movie": "Taylor Swift The Eras Tour Film",
    "year_processed": "2024",
    "global_frequency": 1
  },
  {
    "id": "v_c91f8bcd",
    "word": "Hang your head low",
    "translation": "baja la cabeza, gacha la cabeza",
    "source_movie": "Taylor Swift The Eras Tour Film",
    "year_processed": "2024",
    "global_frequency": 1
  },
  {
    "id": "v_4b870f7c",
    "word": "We’ll screw it up",
    "translation": "la cagaremos, lo arruinaremos",
    "source_movie": "Taylor Swift The Eras Tour Film",
    "year_processed": "2024",
    "global_frequency": 1
  },
  {
    "id": "v_941239d1",
    "word": "Cut the headlights",
    "translation": "cortar los faro",
    "source_movie": "Taylor Swift The Eras Tour Film",
    "year_processed": "2024",
    "global_frequency": 1
  },
  {
    "id": "v_72dd5dd1",
    "word": "I snuck in",
    "translation": "me cole, me meta",
    "source_movie": "Taylor Swift The Eras Tour Film",
    "year_processed": "2024",
    "global_frequency": 1
  },
  {
    "id": "v_7c7eb1e3",
    "word": "Seal (verb)",
    "translation": "sellar",
    "source_movie": "Taylor Swift The Eras Tour Film",
    "year_processed": "2024",
    "global_frequency": 1
  },
  {
    "id": "v_a353b339",
    "word": "Grin (verb)",
    "translation": "sonreir",
    "source_movie": "Taylor Swift The Eras Tour Film",
    "year_processed": "2024",
    "global_frequency": 1
  },
  {
    "id": "v_2fd2edcb",
    "word": "Mouth (verb)",
    "translation": "hablar, decir (algo sin emitir ruido o sonido)",
    "source_movie": "Taylor Swift The Eras Tour Film",
    "year_processed": "2024",
    "global_frequency": 1
  },
  {
    "id": "v_ab6e5a07",
    "word": "Fade out",
    "translation": "desvanecer",
    "source_movie": "Taylor Swift The Eras Tour Film",
    "year_processed": "2024",
    "global_frequency": 1
  },
  {
    "id": "v_c9704f09",
    "word": "Rousing music playing",
    "translation": "buena música alegre",
    "source_movie": "Taylor Swift The Eras Tour Film",
    "year_processed": "2024",
    "global_frequency": 1
  },
  {
    "id": "v_565d2085",
    "word": "Put in the work",
    "translation": "esfuérzate, trabajo",
    "source_movie": "Taylor Swift The Eras Tour Film",
    "year_processed": "2024",
    "global_frequency": 1
  },
  {
    "id": "v_45957b98",
    "word": "If I was rude",
    "translation": "si fu grosero, si fuera grosero",
    "source_movie": "Taylor Swift The Eras Tour Film",
    "year_processed": "2024",
    "global_frequency": 1
  },
  {
    "id": "v_0843950c",
    "word": "Toast (verb en sentimo social)",
    "translation": "brindar",
    "source_movie": "Taylor Swift The Eras Tour Film",
    "year_processed": "2024",
    "global_frequency": 1
  },
  {
    "id": "v_ae0a3b41",
    "word": "dares?",
    "translation": "No registrada",
    "source_movie": "Taylor Swift The Eras Tour Film",
    "year_processed": "2024",
    "global_frequency": 1
  },
  {
    "id": "v_c88f5625",
    "word": "Flash (verb)",
    "translation": "mostrar, destellar, brillar",
    "source_movie": "Taylor Swift The Eras Tour Film",
    "year_processed": "2024",
    "global_frequency": 3
  },
  {
    "id": "v_a5918551",
    "word": "Ballet",
    "translation": "bailarín",
    "source_movie": "Taylor Swift The Eras Tour Film",
    "year_processed": "2024",
    "global_frequency": 2
  },
  {
    "id": "v_79702344",
    "word": "Paint out",
    "translation": "pintar",
    "source_movie": "Taylor Swift The Eras Tour Film",
    "year_processed": "2024",
    "global_frequency": 2
  },
  {
    "id": "v_13231082",
    "word": "Drumroll",
    "translation": "redoble de tamboreo",
    "source_movie": "Taylor Swift The Eras Tour Film",
    "year_processed": "2024",
    "global_frequency": 1
  },
  {
    "id": "v_a74c0ca5",
    "word": "Be glad",
    "translation": "alebrarse, estar contento",
    "source_movie": "Taylor Swift The Eras Tour Film",
    "year_processed": "2024",
    "global_frequency": 1
  },
  {
    "id": "v_b64aae65",
    "word": "Sunshine on the street",
    "translation": "sol en la calle",
    "source_movie": "Taylor Swift The Eras Tour Film",
    "year_processed": "2024",
    "global_frequency": 2
  },
  {
    "id": "v_2943f533",
    "word": "Guitar riff",
    "translation": "rifa de guitarra",
    "source_movie": "Taylor Swift The Eras Tour Film",
    "year_processed": "2024",
    "global_frequency": 1
  },
  {
    "id": "v_162b58a9",
    "word": "Control your urges",
    "translation": "contralar tus impulso",
    "source_movie": "Taylor Swift The Eras Tour Film",
    "year_processed": "2024",
    "global_frequency": 1
  },
  {
    "id": "v_a080ede3",
    "word": "Gown",
    "translation": "vestido (largo)",
    "source_movie": "Taylor Swift The Eras Tour Film",
    "year_processed": "2024",
    "global_frequency": 1
  },
  {
    "id": "v_a75e02d4",
    "word": "Mellow country music",
    "translation": "música contra suave",
    "source_movie": "Taylor Swift The Eras Tour Film",
    "year_processed": "2024",
    "global_frequency": 1
  },
  {
    "id": "v_0e6f0b5c",
    "word": "Delight (substantive)",
    "translation": "deleite, placer",
    "source_movie": "Taylor Swift The Eras Tour Film",
    "year_processed": "2024",
    "global_frequency": 1
  },
  {
    "id": "v_aaaa29ac",
    "word": "Span (verb)",
    "translation": "abarcar",
    "source_movie": "Taylor Swift The Eras Tour Film",
    "year_processed": "2024",
    "global_frequency": 2
  },
  {
    "id": "v_1b5c4bf7",
    "word": "Out and about in the world",
    "translation": "en todo el mundo, por el mundo",
    "source_movie": "Taylor Swift The Eras Tour Film",
    "year_processed": "2024",
    "global_frequency": 1
  },
  {
    "id": "v_b5738314",
    "word": "A dazzling haze",
    "translation": "una neblina deslumbrante",
    "source_movie": "Taylor Swift The Eras Tour Film",
    "year_processed": "2024",
    "global_frequency": 2
  },
  {
    "id": "v_55c65e5f",
    "word": "Intriguing music",
    "translation": "música intrigante",
    "source_movie": "Taylor Swift The Eras Tour Film",
    "year_processed": "2024",
    "global_frequency": 1
  },
  {
    "id": "v_1eef0f34",
    "word": "I ride off alone",
    "translation": "me hoy sola",
    "source_movie": "Taylor Swift The Eras Tour Film",
    "year_processed": "2024",
    "global_frequency": 3
  },
  {
    "id": "v_92a9d8d2",
    "word": "Hold on to you",
    "translation": "aferrar a ti, agarrar a ti",
    "source_movie": "Taylor Swift The Eras Tour Film",
    "year_processed": "2024",
    "global_frequency": 1
  },
  {
    "id": "v_21118f75",
    "word": "Spite (verb)",
    "translation": "fastidiar",
    "source_movie": "Taylor Swift The Eras Tour Film",
    "year_processed": "2024",
    "global_frequency": 5
  },
  {
    "id": "v_96b78538",
    "word": "There’s a glow off the pavement",
    "translation": "ha un resplandor en el pavimento",
    "source_movie": "Taylor Swift The Eras Tour Film",
    "year_processed": "2024",
    "global_frequency": 1
  },
  {
    "id": "v_df1ca9ad",
    "word": "I’m trying so hard not to get caught up now",
    "translation": "esto tratado de no quedar atrasado",
    "source_movie": "Taylor Swift The Eras Tour Film",
    "year_processed": "2024",
    "global_frequency": 1
  },
  {
    "id": "v_6ba87034",
    "word": "hora",
    "translation": "No registrada",
    "source_movie": "Taylor Swift The Eras Tour Film",
    "year_processed": "2024",
    "global_frequency": 2
  },
  {
    "id": "v_d351e154",
    "word": "Absentmindedly",
    "translation": "distraídamente",
    "source_movie": "Taylor Swift The Eras Tour Film",
    "year_processed": "2024",
    "global_frequency": 1
  },
  {
    "id": "v_8160edb4",
    "word": "Headfirst",
    "translation": "de cabeza",
    "source_movie": "Taylor Swift The Eras Tour Film",
    "year_processed": "2024",
    "global_frequency": 1
  },
  {
    "id": "v_294ec7ec",
    "word": "Doorway",
    "translation": "puerta",
    "source_movie": "Taylor Swift The Eras Tour Film",
    "year_processed": "2024",
    "global_frequency": 2
  },
  {
    "id": "v_d662cd59",
    "word": "Pull in",
    "translation": "tirar, arrastrar",
    "source_movie": "Taylor Swift The Eras Tour Film",
    "year_processed": "2024",
    "global_frequency": 2
  },
  {
    "id": "v_da518abd",
    "word": "Flawless",
    "translation": "impecable",
    "source_movie": "Taylor Swift The Eras Tour Film",
    "year_processed": "2024",
    "global_frequency": 1
  },
  {
    "id": "v_27298997",
    "word": "Go off",
    "translation": "ir",
    "source_movie": "Taylor Swift The Eras Tour Film",
    "year_processed": "2024",
    "global_frequency": 6
  },
  {
    "id": "v_16413227",
    "word": "Bleachers",
    "translation": "grada, tribunal",
    "source_movie": "Taylor Swift The Eras Tour Film",
    "year_processed": "2024",
    "global_frequency": 1
  },
  {
    "id": "v_61109ee5",
    "word": "You belong with me",
    "translation": "tú me pertenecer",
    "source_movie": "Taylor Swift The Eras Tour Film",
    "year_processed": "2024",
    "global_frequency": 1
  },
  {
    "id": "v_020cc391",
    "word": "Worn-out jeans",
    "translation": "jesús desgastador",
    "source_movie": "Taylor Swift The Eras Tour Film",
    "year_processed": "2024",
    "global_frequency": 1
  },
  {
    "id": "v_13243d70",
    "word": "Park bench",
    "translation": "banco del parque (alusivo al asiento de dicho lugar)",
    "source_movie": "Taylor Swift The Eras Tour Film",
    "year_processed": "2024",
    "global_frequency": 1
  },
  {
    "id": "v_32fe31e7",
    "word": "Light up",
    "translation": "iluminar",
    "source_movie": "Taylor Swift The Eras Tour Film",
    "year_processed": "2024",
    "global_frequency": 4
  },
  {
    "id": "v_19fc3081",
    "word": "Bring down",
    "translation": "derribar, hacer caer, hundir",
    "source_movie": "Taylor Swift The Eras Tour Film",
    "year_processed": "2024",
    "global_frequency": 6
  },
  {
    "id": "v_4c3cdcdc",
    "word": "Stand by",
    "translation": "esperar",
    "source_movie": "Taylor Swift The Eras Tour Film",
    "year_processed": "2024",
    "global_frequency": 2
  },
  {
    "id": "v_e7ff8fb9",
    "word": "The ball gowns",
    "translation": "los vestido de baile",
    "source_movie": "Taylor Swift The Eras Tour Film",
    "year_processed": "2024",
    "global_frequency": 1
  },
  {
    "id": "v_c6cfe5aa",
    "word": "You make your way",
    "translation": "te ares paso",
    "source_movie": "Taylor Swift The Eras Tour Film",
    "year_processed": "2024",
    "global_frequency": 1
  },
  {
    "id": "v_eecffa96",
    "word": "Little did I know",
    "translation": "poco sabia yo, no sabia",
    "source_movie": "Taylor Swift The Eras Tour Film",
    "year_processed": "2024",
    "global_frequency": 1
  },
  {
    "id": "v_841379de",
    "word": "Pebbles",
    "translation": "piedrecitas",
    "source_movie": "Taylor Swift The Eras Tour Film",
    "year_processed": "2024",
    "global_frequency": 2
  },
  {
    "id": "v_71fd4992",
    "word": "Staircase",
    "translation": "escalera",
    "source_movie": "Taylor Swift The Eras Tour Film",
    "year_processed": "2024",
    "global_frequency": 1
  },
  {
    "id": "v_d07f0c34",
    "word": "Sneak out",
    "translation": "descabullirse",
    "source_movie": "Taylor Swift The Eras Tour Film",
    "year_processed": "2024",
    "global_frequency": 3
  },
  {
    "id": "v_4e1b5ef2",
    "word": "We’ll make it out of this mess",
    "translation": "saldremos de este lío/desastre",
    "source_movie": "Taylor Swift The Eras Tour Film",
    "year_processed": "2024",
    "global_frequency": 1
  },
  {
    "id": "v_d14f0810",
    "word": "Fade (verb)",
    "translation": "desvanecer, desaparecer",
    "source_movie": "Taylor Swift The Eras Tour Film",
    "year_processed": "2024",
    "global_frequency": 2
  },
  {
    "id": "v_7035dfa3",
    "word": "The outskirts of town",
    "translation": "las afuera del pueblo",
    "source_movie": "Taylor Swift The Eras Tour Film",
    "year_processed": "2024",
    "global_frequency": 1
  },
  {
    "id": "v_a58dbe77",
    "word": "Pull out",
    "translation": "sacar",
    "source_movie": "Taylor Swift The Eras Tour Film",
    "year_processed": "2024",
    "global_frequency": 3
  },
  {
    "id": "v_54276b3b",
    "word": "Pick out",
    "translation": "elegir, escoger",
    "source_movie": "Taylor Swift The Eras Tour Film",
    "year_processed": "2024",
    "global_frequency": 2
  },
  {
    "id": "v_9ab8562b",
    "word": "When your ship rolled in that night",
    "translation": "cuando tu barco llega esa noche",
    "source_movie": "Taylor Swift The Eras Tour Film",
    "year_processed": "2024",
    "global_frequency": 1
  },
  {
    "id": "v_846b30f3",
    "word": "Rough on the surface",
    "translation": "áspero en la superficie",
    "source_movie": "Taylor Swift The Eras Tour Film",
    "year_processed": "2024",
    "global_frequency": 1
  },
  {
    "id": "v_f044f11f",
    "word": "Open-shut case",
    "translation": "caso abierto-cerrado, caso de apertura y cierre",
    "source_movie": "Taylor Swift The Eras Tour Film",
    "year_processed": "2024",
    "global_frequency": 1
  },
  {
    "id": "v_7c273262",
    "word": "A wine priceless",
    "translation": "un vino que no tizne precio",
    "source_movie": "Taylor Swift The Eras Tour Film",
    "year_processed": "2024",
    "global_frequency": 1
  },
  {
    "id": "v_d5485feb",
    "word": "Wherever you stray",
    "translation": "dondequiera que te mierda",
    "source_movie": "Taylor Swift The Eras Tour Film",
    "year_processed": "2024",
    "global_frequency": 1
  },
  {
    "id": "v_f0b11370",
    "word": "Wreck (verb)",
    "translation": "arruinar, destrozar, estropear",
    "source_movie": "Taylor Swift The Eras Tour Film",
    "year_processed": "2024",
    "global_frequency": 5
  },
  {
    "id": "v_0a890803",
    "word": "Willow",
    "translation": "sauce",
    "source_movie": "Taylor Swift The Eras Tour Film",
    "year_processed": "2024",
    "global_frequency": 1
  },
  {
    "id": "v_bb559222",
    "word": "Sneak in",
    "translation": "clase",
    "source_movie": "Taylor Swift The Eras Tour Film",
    "year_processed": "2024",
    "global_frequency": 2
  },
  {
    "id": "v_ebe2fe78",
    "word": "Champion ring",
    "translation": "anillo de campeón",
    "source_movie": "Taylor Swift The Eras Tour Film",
    "year_processed": "2024",
    "global_frequency": 1
  },
  {
    "id": "v_5b1f9352",
    "word": "Anywhere else is hollow",
    "translation": "Cualquier otro lugar esta vaco",
    "source_movie": "Taylor Swift The Eras Tour Film",
    "year_processed": "2024",
    "global_frequency": 1
  },
  {
    "id": "v_8f37cc4e",
    "word": "Count out",
    "translation": "echar, descartar, dejar fuera",
    "source_movie": "Taylor Swift The Eras Tour Film",
    "year_processed": "2024",
    "global_frequency": 2
  },
  {
    "id": "v_51069f61",
    "word": "Every bait and switch",
    "translation": "cada cebo y cambio",
    "source_movie": "Taylor Swift The Eras Tour Film",
    "year_processed": "2024",
    "global_frequency": 1
  },
  {
    "id": "v_f29e4b98",
    "word": "The autumn chill",
    "translation": "el frío del otoño",
    "source_movie": "Taylor Swift The Eras Tour Film",
    "year_processed": "2024",
    "global_frequency": 1
  },
  {
    "id": "v_a12b0bb0",
    "word": "The amber skies",
    "translation": "los cielo ámbar",
    "source_movie": "Taylor Swift The Eras Tour Film",
    "year_processed": "2024",
    "global_frequency": 1
  },
  {
    "id": "v_798a6f39",
    "word": "Long limbs and frozen swims",
    "translation": "larga extremidad y nado helado",
    "source_movie": "Taylor Swift The Eras Tour Film",
    "year_processed": "2024",
    "global_frequency": 1
  },
  {
    "id": "v_2f0b360d",
    "word": "Ride back",
    "translation": "viaje de vuelta",
    "source_movie": "Taylor Swift The Eras Tour Film",
    "year_processed": "2024",
    "global_frequency": 1
  },
  {
    "id": "v_5af91bfe",
    "word": "Scrap",
    "translation": "tocino, cedacito",
    "source_movie": "Taylor Swift The Eras Tour Film",
    "year_processed": "2024",
    "global_frequency": 4
  },
  {
    "id": "v_40737d5c",
    "word": "Backlogged dreams",
    "translation": "sueño atrasado, sueño atascado",
    "source_movie": "Taylor Swift The Eras Tour Film",
    "year_processed": "2024",
    "global_frequency": 1
  },
  {
    "id": "v_c756422a",
    "word": "Fumble (verb)",
    "translation": "titubear",
    "source_movie": "Taylor Swift The Eras Tour Film",
    "year_processed": "2024",
    "global_frequency": 1
  },
  {
    "id": "v_21562930",
    "word": "Audience whoops",
    "translation": "audiencia gitano",
    "source_movie": "Taylor Swift The Eras Tour Film",
    "year_processed": "2024",
    "global_frequency": 1
  },
  {
    "id": "v_9695153e",
    "word": "Clicks tongue",
    "translation": "chasquear la lengua",
    "source_movie": "Taylor Swift The Eras Tour Film",
    "year_processed": "2024",
    "global_frequency": 2
  },
  {
    "id": "v_f6703efa",
    "word": "Cathartic",
    "translation": "catártico",
    "source_movie": "Taylor Swift The Eras Tour Film",
    "year_processed": "2024",
    "global_frequency": 1
  },
  {
    "id": "v_568cf888",
    "word": "Bustling crowds or silent sleepers",
    "translation": "multitud bulliciosa o durmiente silencioso",
    "source_movie": "Taylor Swift The Eras Tour Film",
    "year_processed": "2024",
    "global_frequency": 1
  },
  {
    "id": "v_791e8b4e",
    "word": "Left you out there standing",
    "translation": "te deja ahí de pie",
    "source_movie": "Taylor Swift The Eras Tour Film",
    "year_processed": "2024",
    "global_frequency": 1
  },
  {
    "id": "v_e6e83eb7",
    "word": "Crestfallen on the landing",
    "translation": "cabizbajo en el rellano",
    "source_movie": "Taylor Swift The Eras Tour Film",
    "year_processed": "2024",
    "global_frequency": 1
  },
  {
    "id": "v_64bddb1b",
    "word": "You could’t keep it in",
    "translation": "no sudeste retener",
    "source_movie": "Taylor Swift The Eras Tour Film",
    "year_processed": "2024",
    "global_frequency": 1
  },
  {
    "id": "v_d7fdc1bc",
    "word": "Splash out",
    "translation": "derrochar",
    "source_movie": "Taylor Swift The Eras Tour Film",
    "year_processed": "2024",
    "global_frequency": 1
  },
  {
    "id": "v_66986a9b",
    "word": "Hometown skeptics",
    "translation": "escéptico local",
    "source_movie": "Taylor Swift The Eras Tour Film",
    "year_processed": "2024",
    "global_frequency": 1
  },
  {
    "id": "v_6b3477b7",
    "word": "You’re speechless",
    "translation": "te queda sin palabra",
    "source_movie": "Taylor Swift The Eras Tour Film",
    "year_processed": "2024",
    "global_frequency": 1
  },
  {
    "id": "v_cb3311bd",
    "word": "November flush and flannel cure",
    "translation": "enrojecimiento/enjuague de noviembre y cura de",
    "source_movie": "Taylor Swift The Eras Tour Film",
    "year_processed": "2024",
    "global_frequency": 1
  },
  {
    "id": "v_22c729f8",
    "word": "frankly",
    "translation": "No registrada",
    "source_movie": "Taylor Swift The Eras Tour Film",
    "year_processed": "2024",
    "global_frequency": 1
  },
  {
    "id": "v_04578f8b",
    "word": "Madhouse",
    "translation": "manicomio",
    "source_movie": "Taylor Swift The Eras Tour Film",
    "year_processed": "2024",
    "global_frequency": 2
  },
  {
    "id": "v_e95cf5f5",
    "word": "How evergreen",
    "translation": "que perenne, que siempre verde",
    "source_movie": "Taylor Swift The Eras Tour Film",
    "year_processed": "2024",
    "global_frequency": 1
  },
  {
    "id": "v_7dd3e59c",
    "word": "The nerve to deck the halls",
    "translation": "el valor de engalanar/decorar los pasillo",
    "source_movie": "Taylor Swift The Eras Tour Film",
    "year_processed": "2024",
    "global_frequency": 1
  },
  {
    "id": "v_13b90d57",
    "word": "The real thing",
    "translation": "lo auténtico, lo verdadero",
    "source_movie": "Taylor Swift The Eras Tour Film",
    "year_processed": "2024",
    "global_frequency": 1
  },
  {
    "id": "v_086877ab",
    "word": "She’ll patch up your tapestry that I shred",
    "translation": "ella remendar tu tapiz que yo destrozo",
    "source_movie": "Taylor Swift The Eras Tour Film",
    "year_processed": "2024",
    "global_frequency": 1
  },
  {
    "id": "v_49249604",
    "word": "By the door",
    "translation": "junto a la puerta",
    "source_movie": "Taylor Swift The Eras Tour Film",
    "year_processed": "2024",
    "global_frequency": 1
  },
  {
    "id": "v_d24ac6bb",
    "word": "Lay the table",
    "translation": "poner la mesa",
    "source_movie": "Taylor Swift The Eras Tour Film",
    "year_processed": "2024",
    "global_frequency": 1
  },
  {
    "id": "v_68802908",
    "word": "Blankets",
    "translation": "manta, cobija",
    "source_movie": "Taylor Swift The Eras Tour Film",
    "year_processed": "2024",
    "global_frequency": 1
  },
  {
    "id": "v_b3ac9e33",
    "word": "Barbed wire",
    "translation": "alambre de espino",
    "source_movie": "Taylor Swift The Eras Tour Film",
    "year_processed": "2024",
    "global_frequency": 2
  },
  {
    "id": "v_30e7f7dc",
    "word": "Footnotes",
    "translation": "nota a pie de página",
    "source_movie": "Taylor Swift The Eras Tour Film",
    "year_processed": "2024",
    "global_frequency": 2
  },
  {
    "id": "v_87e48507",
    "word": "Byline",
    "translation": "línea de fondo",
    "source_movie": "Taylor Swift The Eras Tour Film",
    "year_processed": "2024",
    "global_frequency": 2
  },
  {
    "id": "v_9edd94b4",
    "word": "Break free",
    "translation": "librote",
    "source_movie": "Taylor Swift The Eras Tour Film",
    "year_processed": "2024",
    "global_frequency": 1
  },
  {
    "id": "v_eebd529c",
    "word": "Took this dagger in me",
    "translation": "me clavo esta daga",
    "source_movie": "Taylor Swift The Eras Tour Film",
    "year_processed": "2024",
    "global_frequency": 1
  },
  {
    "id": "v_6c62c5ea",
    "word": "Electricity crackling",
    "translation": "crepitaciones eléctrica",
    "source_movie": "Taylor Swift The Eras Tour Film",
    "year_processed": "2024",
    "global_frequency": 1
  },
  {
    "id": "v_35dfe10b",
    "word": "Faint, intriguing music",
    "translation": "música tenue e intrigante",
    "source_movie": "Taylor Swift The Eras Tour Film",
    "year_processed": "2024",
    "global_frequency": 1
  },
  {
    "id": "v_b917f485",
    "word": "Snake rattling",
    "translation": "serpiente traqueteando",
    "source_movie": "Taylor Swift The Eras Tour Film",
    "year_processed": "2024",
    "global_frequency": 1
  },
  {
    "id": "v_2929a38a",
    "word": "Clack (verb)",
    "translation": "sonar",
    "source_movie": "Taylor Swift The Eras Tour Film",
    "year_processed": "2024",
    "global_frequency": 1
  },
  {
    "id": "v_5bb66cc3",
    "word": "Holding him for ransom",
    "translation": "pedir un rescate por él",
    "source_movie": "Taylor Swift The Eras Tour Film",
    "year_processed": "2024",
    "global_frequency": 2
  },
  {
    "id": "v_983a5bcf",
    "word": "Island breeze",
    "translation": "brisa isleña",
    "source_movie": "Taylor Swift The Eras Tour Film",
    "year_processed": "2024",
    "global_frequency": 1
  },
  {
    "id": "v_a8a91567",
    "word": "And lights down low",
    "translation": "y lunes baja",
    "source_movie": "Taylor Swift The Eras Tour Film",
    "year_processed": "2024",
    "global_frequency": 2
  },
  {
    "id": "v_43886aa0",
    "word": "Run off",
    "translation": "huir, escapar",
    "source_movie": "Taylor Swift The Eras Tour Film",
    "year_processed": "2024",
    "global_frequency": 2
  },
  {
    "id": "v_a8d7951d",
    "word": "Jailer",
    "translation": "carcelero",
    "source_movie": "Taylor Swift The Eras Tour Film",
    "year_processed": "2024",
    "global_frequency": 2
  },
  {
    "id": "v_0aa905c1",
    "word": "I’m so very tame",
    "translation": "son muy manso, son muy dócil",
    "source_movie": "Taylor Swift The Eras Tour Film",
    "year_processed": "2024",
    "global_frequency": 2
  },
  {
    "id": "v_d832cadb",
    "word": "Dive bar",
    "translation": "pequeño bar",
    "source_movie": "Taylor Swift The Eras Tour Film",
    "year_processed": "2024",
    "global_frequency": 2
  },
  {
    "id": "v_ad7db04b",
    "word": "Nightstand",
    "translation": "meseta de noche",
    "source_movie": "Taylor Swift The Eras Tour Film",
    "year_processed": "2024",
    "global_frequency": 1
  },
  {
    "id": "v_b681ad49",
    "word": "Black (en terminus de luminosidad)",
    "translation": "oscuridad",
    "source_movie": "Taylor Swift The Eras Tour Film",
    "year_processed": "2024",
    "global_frequency": 1
  },
  {
    "id": "v_add79660",
    "word": "Pace (verb)",
    "translation": "deambular, caminar (de un lado a otro)",
    "source_movie": "Taylor Swift The Eras Tour Film",
    "year_processed": "2024",
    "global_frequency": 3
  },
  {
    "id": "v_d7772d39",
    "word": "I get so high",
    "translation": "esto tan rogado",
    "source_movie": "Taylor Swift The Eras Tour Film",
    "year_processed": "2024",
    "global_frequency": 1
  },
  {
    "id": "v_ddad7a4f",
    "word": "Tilted stage",
    "translation": "escenario inclinado",
    "source_movie": "Taylor Swift The Eras Tour Film",
    "year_processed": "2024",
    "global_frequency": 2
  },
  {
    "id": "v_fd7a5a36",
    "word": "Get harder",
    "translation": "endurecer",
    "source_movie": "Taylor Swift The Eras Tour Film",
    "year_processed": "2024",
    "global_frequency": 1
  },
  {
    "id": "v_7edee0b9",
    "word": "In the nick of time",
    "translation": "en el último momento",
    "source_movie": "Taylor Swift The Eras Tour Film",
    "year_processed": "2024",
    "global_frequency": 2
  },
  {
    "id": "v_01696ae3",
    "word": "Rose up",
    "translation": "resucitar, levantar",
    "source_movie": "Taylor Swift The Eras Tour Film",
    "year_processed": "2024",
    "global_frequency": 1
  },
  {
    "id": "v_f2fa124c",
    "word": "Locked me out and threw a beast",
    "translation": "Me encerrar fuera y organizar un banquete",
    "source_movie": "Taylor Swift The Eras Tour Film",
    "year_processed": "2024",
    "global_frequency": 2
  },
  {
    "id": "v_8a23b2af",
    "word": "Star (verb en terminus de actuation)",
    "translation": "protagonizar",
    "source_movie": "Taylor Swift The Eras Tour Film",
    "year_processed": "2024",
    "global_frequency": 2
  },
  {
    "id": "v_53f6345d",
    "word": "Shifting eyes and vacancy",
    "translation": "ojo cambiante y vaco",
    "source_movie": "Taylor Swift The Eras Tour Film",
    "year_processed": "2024",
    "global_frequency": 1
  },
  {
    "id": "v_fad871e6",
    "word": "Vanish (verb)",
    "translation": "desaparecer, desvanecer",
    "source_movie": "Taylor Swift The Eras Tour Film",
    "year_processed": "2024",
    "global_frequency": 3
  },
  {
    "id": "v_3df66019",
    "word": "Playful conversation",
    "translation": "conversación lúdicra",
    "source_movie": "Taylor Swift The Eras Tour Film",
    "year_processed": "2024",
    "global_frequency": 1
  },
  {
    "id": "v_9555d9ca",
    "word": "Counter all your quick remarks",
    "translation": "contrarrestar todo tus comentario rápido",
    "source_movie": "Taylor Swift The Eras Tour Film",
    "year_processed": "2024",
    "global_frequency": 1
  },
  {
    "id": "v_a839c0c0",
    "word": "In secrecy",
    "translation": "en secreto, a escondidas",
    "source_movie": "Taylor Swift The Eras Tour Film",
    "year_processed": "2024",
    "global_frequency": 1
  },
  {
    "id": "v_402ec3a5",
    "word": "Wonderstruck",
    "translation": "asombrador, maravilloso",
    "source_movie": "Taylor Swift The Eras Tour Film",
    "year_processed": "2024",
    "global_frequency": 1
  },
  {
    "id": "v_c8994b8c",
    "word": "Read off",
    "translation": "leer",
    "source_movie": "Taylor Swift The Eras Tour Film",
    "year_processed": "2024",
    "global_frequency": 1
  },
  {
    "id": "v_8ce7a6fa",
    "word": "Bring on",
    "translation": "traer (persona)",
    "source_movie": "Taylor Swift The Eras Tour Film",
    "year_processed": "2024",
    "global_frequency": 3
  },
  {
    "id": "v_596aaeba",
    "word": "On the sidelines wishing for right now",
    "translation": "al margen descanso que ahora mismo",
    "source_movie": "Taylor Swift The Eras Tour Film",
    "year_processed": "2024",
    "global_frequency": 1
  },
  {
    "id": "v_cb7a1054",
    "word": "Baseball cap",
    "translation": "gorra de béisbol",
    "source_movie": "Taylor Swift The Eras Tour Film",
    "year_processed": "2024",
    "global_frequency": 1
  },
  {
    "id": "v_177b107b",
    "word": "We held them up",
    "translation": "los sostuvimos, los retuvimos",
    "source_movie": "Taylor Swift The Eras Tour Film",
    "year_processed": "2024",
    "global_frequency": 1
  },
  {
    "id": "v_6a69b5a3",
    "word": "The cynics were outraged",
    "translation": "los cínico se indignar",
    "source_movie": "Taylor Swift The Eras Tour Film",
    "year_processed": "2024",
    "global_frequency": 1
  },
  {
    "id": "v_a5d388bd",
    "word": "Ripped-up jeans",
    "translation": "jesús roto",
    "source_movie": "Taylor Swift The Eras Tour Film",
    "year_processed": "2024",
    "global_frequency": 1
  },
  {
    "id": "v_610409ed",
    "word": "Step in",
    "translation": "intervenir",
    "source_movie": "Taylor Swift The Eras Tour Film",
    "year_processed": "2024",
    "global_frequency": 5
  },
  {
    "id": "v_74ef493d",
    "word": "Background singers vocalizing",
    "translation": "cantante de fondo vocalizador",
    "source_movie": "Taylor Swift The Eras Tour Film",
    "year_processed": "2024",
    "global_frequency": 1
  },
  {
    "id": "v_bfdbd1fb",
    "word": "The crowds in stands",
    "translation": "la multitud en las grada",
    "source_movie": "Taylor Swift The Eras Tour Film",
    "year_processed": "2024",
    "global_frequency": 1
  },
  {
    "id": "v_1f2267ab",
    "word": "Pray (verb)",
    "translation": "orar, rezar",
    "source_movie": "Taylor Swift The Eras Tour Film",
    "year_processed": "2024",
    "global_frequency": 1
  },
  {
    "id": "v_fd1b051e",
    "word": "Hold back",
    "translation": "contener, retener",
    "source_movie": "Taylor Swift The Eras Tour Film",
    "year_processed": "2024",
    "global_frequency": 4
  },
  {
    "id": "v_979d6628",
    "word": "Faint drumroll",
    "translation": "leve redoble de tamboreo",
    "source_movie": "Taylor Swift The Eras Tour Film",
    "year_processed": "2024",
    "global_frequency": 1
  },
  {
    "id": "v_551a61bb",
    "word": "Keep (verb en cheetos contexts)",
    "translation": "tener, mantener (a alguien a tu lado)",
    "source_movie": "Taylor Swift The Eras Tour Film",
    "year_processed": "2024",
    "global_frequency": 1
  },
  {
    "id": "v_417d4869",
    "word": "Ditch (verb)",
    "translation": "deshacer",
    "source_movie": "Taylor Swift The Eras Tour Film",
    "year_processed": "2024",
    "global_frequency": 7
  },
  {
    "id": "v_09856966",
    "word": "Heartbreaks",
    "translation": "desamor, desengaño",
    "source_movie": "Taylor Swift The Eras Tour Film",
    "year_processed": "2024",
    "global_frequency": 1
  },
  {
    "id": "v_a9a73ebc",
    "word": "Come around",
    "translation": "volver",
    "source_movie": "Taylor Swift The Eras Tour Film",
    "year_processed": "2024",
    "global_frequency": 3
  },
  {
    "id": "v_fae0ebe6",
    "word": "We called it off again",
    "translation": "lo cancelamos de nuevo",
    "source_movie": "Taylor Swift The Eras Tour Film",
    "year_processed": "2024",
    "global_frequency": 1
  },
  {
    "id": "v_370c0978",
    "word": "And me falling for it",
    "translation": "y yo cayado en la trampa",
    "source_movie": "Taylor Swift The Eras Tour Film",
    "year_processed": "2024",
    "global_frequency": 1
  },
  {
    "id": "v_90abad5c",
    "word": "Hide away",
    "translation": "ocultar, esconder",
    "source_movie": "Taylor Swift The Eras Tour Film",
    "year_processed": "2024",
    "global_frequency": 2
  },
  {
    "id": "v_a76a308f",
    "word": "Call up",
    "translation": "llamar",
    "source_movie": "Taylor Swift The Eras Tour Film",
    "year_processed": "2024",
    "global_frequency": 1
  },
  {
    "id": "v_d043c94e",
    "word": "Sights",
    "translation": "mira, punto de mira",
    "source_movie": "Taylor Swift The Eras Tour Film",
    "year_processed": "2024",
    "global_frequency": 2
  },
  {
    "id": "v_a15380f0",
    "word": "Fall hard",
    "translation": "caer con fuerza, caer fuerte",
    "source_movie": "Taylor Swift The Eras Tour Film",
    "year_processed": "2024",
    "global_frequency": 1
  },
  {
    "id": "v_71609e88",
    "word": "Step back",
    "translation": "dar un paso atrás",
    "source_movie": "Taylor Swift The Eras Tour Film",
    "year_processed": "2024",
    "global_frequency": 1
  },
  {
    "id": "v_e7f9bae1",
    "word": "He’s long gone",
    "translation": "hacer tiempo que se ha do",
    "source_movie": "Taylor Swift The Eras Tour Film",
    "year_processed": "2024",
    "global_frequency": 1
  },
  {
    "id": "v_69dddb03",
    "word": "I’m lying on the cold hard ground",
    "translation": "esto tendido/tumbado/tirado en el duro y frío",
    "source_movie": "Taylor Swift The Eras Tour Film",
    "year_processed": "2024",
    "global_frequency": 1
  },
  {
    "id": "v_bec285a1",
    "word": "sell",
    "translation": "No registrada",
    "source_movie": "Taylor Swift The Eras Tour Film",
    "year_processed": "2024",
    "global_frequency": 1
  },
  {
    "id": "v_ef977a6c",
    "word": "Creep in",
    "translation": "arrastrar, acercar sigilosamente",
    "source_movie": "Taylor Swift The Eras Tour Film",
    "year_processed": "2024",
    "global_frequency": 1
  },
  {
    "id": "v_098e6913",
    "word": "minutes libras?",
    "translation": "No registrada",
    "source_movie": "Taylor Swift The Eras Tour Film",
    "year_processed": "2024",
    "global_frequency": 1
  },
  {
    "id": "v_907ea3e2",
    "word": "Wide-eyed gaze",
    "translation": "mirada de ojo abierto",
    "source_movie": "Taylor Swift The Eras Tour Film",
    "year_processed": "2024",
    "global_frequency": 2
  },
  {
    "id": "v_2156d8df",
    "word": "Getting lost upstate",
    "translation": "perdiéndonos al norte del estado",
    "source_movie": "Taylor Swift The Eras Tour Film",
    "year_processed": "2024",
    "global_frequency": 1
  },
  {
    "id": "v_eb7c016d",
    "word": "Look over at me",
    "translation": "mirar",
    "source_movie": "Taylor Swift The Eras Tour Film",
    "year_processed": "2024",
    "global_frequency": 1
  },
  {
    "id": "v_35588dcf",
    "word": "Twin-sized bed",
    "translation": "cama de matrimonio",
    "source_movie": "Taylor Swift The Eras Tour Film",
    "year_processed": "2024",
    "global_frequency": 1
  },
  {
    "id": "v_bea3cbc7",
    "word": "Tee-ball team",
    "translation": "equipo de te-bala",
    "source_movie": "Taylor Swift The Eras Tour Film",
    "year_processed": "2024",
    "global_frequency": 1
  },
  {
    "id": "v_56d9aacd",
    "word": "Enchain",
    "translation": "llavero",
    "source_movie": "Taylor Swift The Eras Tour Film",
    "year_processed": "2024",
    "global_frequency": 1
  },
  {
    "id": "v_b0aebf0c",
    "word": "The drive down",
    "translation": "el camino, el viaje",
    "source_movie": "Taylor Swift The Eras Tour Film",
    "year_processed": "2024",
    "global_frequency": 1
  },
  {
    "id": "v_4af52286",
    "word": "Grave",
    "translation": "tumba",
    "source_movie": "Taylor Swift The Eras Tour Film",
    "year_processed": "2024",
    "global_frequency": 2
  },
  {
    "id": "v_b88fa29e",
    "word": "As I reached for you",
    "translation": "mientras te buscada",
    "source_movie": "Taylor Swift The Eras Tour Film",
    "year_processed": "2024",
    "global_frequency": 1
  },
  {
    "id": "v_0f5f8f34",
    "word": "My lifeless frame",
    "translation": "mi cuerpo sin vida",
    "source_movie": "Taylor Swift The Eras Tour Film",
    "year_processed": "2024",
    "global_frequency": 1
  },
  {
    "id": "v_ec9eafff",
    "word": "Oath",
    "translation": "juramento",
    "source_movie": "Taylor Swift The Eras Tour Film",
    "year_processed": "2024",
    "global_frequency": 3
  },
  {
    "id": "v_0da7fc5d",
    "word": "Prayer",
    "translation": "oración, rezo, plegaria",
    "source_movie": "Taylor Swift The Eras Tour Film",
    "year_processed": "2024",
    "global_frequency": 6
  },
  {
    "id": "v_b541e003",
    "word": "Tear up",
    "translation": "romper, destrozar",
    "source_movie": "Taylor Swift The Eras Tour Film",
    "year_processed": "2024",
    "global_frequency": 5
  },
  {
    "id": "v_bf480b43",
    "word": "I’m a crumpled up piece of paper",
    "translation": "son un trozo de papel arrufado",
    "source_movie": "Taylor Swift The Eras Tour Film",
    "year_processed": "2024",
    "global_frequency": 1
  },
  {
    "id": "v_77fdaeba",
    "word": "Double-cross (verb)",
    "translation": "engañar, traicionar",
    "source_movie": "Taylor Swift The Eras Tour Film",
    "year_processed": "2024",
    "global_frequency": 4
  },
  {
    "id": "v_8174fac0",
    "word": "A never-needy ever-lonely jewel",
    "translation": "una joya nunca necesitada y siempre sola",
    "source_movie": "Taylor Swift The Eras Tour Film",
    "year_processed": "2024",
    "global_frequency": 1
  },
  {
    "id": "v_499b91c2",
    "word": "Charm (verb)",
    "translation": "encandilar, encantar",
    "source_movie": "Taylor Swift The Eras Tour Film",
    "year_processed": "2024",
    "global_frequency": 1
  },
  {
    "id": "v_5b2c7525",
    "word": "Self-effacing jokes",
    "translation": "chiste autocomplacientes, chiste sobre uno mismo",
    "source_movie": "Taylor Swift The Eras Tour Film",
    "year_processed": "2024",
    "global_frequency": 1
  },
  {
    "id": "v_7fc9251f",
    "word": "Plaid shirt",
    "translation": "camisa a cuadro",
    "source_movie": "Taylor Swift The Eras Tour Film",
    "year_processed": "2024",
    "global_frequency": 2
  },
  {
    "id": "v_3c6197fd",
    "word": "You made me your own",
    "translation": "tú me chiste tuya",
    "source_movie": "Taylor Swift The Eras Tour Film",
    "year_processed": "2024",
    "global_frequency": 1
  },
  {
    "id": "v_f081b6d7",
    "word": "Punch line",
    "translation": "remate (de un chiste)",
    "source_movie": "Taylor Swift The Eras Tour Film",
    "year_processed": "2024",
    "global_frequency": 1
  },
  {
    "id": "v_4eafc1bc",
    "word": "Stay my age",
    "translation": "seguir teniente mi edad",
    "source_movie": "Taylor Swift The Eras Tour Film",
    "year_processed": "2024",
    "global_frequency": 1
  },
  {
    "id": "v_57cfa945",
    "word": "Twin flame bruise",
    "translation": "hematoma de llama gemela",
    "source_movie": "Taylor Swift The Eras Tour Film",
    "year_processed": "2024",
    "global_frequency": 1
  },
  {
    "id": "v_49f3de35",
    "word": "Maim (verb)",
    "translation": "mutilar",
    "source_movie": "Taylor Swift The Eras Tour Film",
    "year_processed": "2024",
    "global_frequency": 1
  },
  {
    "id": "v_a74db1b4",
    "word": "In this city’s barren cold",
    "translation": "en el frío estéril de esta ciudad",
    "source_movie": "Taylor Swift The Eras Tour Film",
    "year_processed": "2024",
    "global_frequency": 1
  },
  {
    "id": "v_fa5c3376",
    "word": "Glisten (verb)",
    "translation": "brillar, relucir",
    "source_movie": "Taylor Swift The Eras Tour Film",
    "year_processed": "2024",
    "global_frequency": 3
  },
  {
    "id": "v_2eaa3e5f",
    "word": "Crickets chirping",
    "translation": "grillos graznido, grillos trinado",
    "source_movie": "Taylor Swift The Eras Tour Film",
    "year_processed": "2024",
    "global_frequency": 3
  },
  {
    "id": "v_d9997828",
    "word": "Matinée",
    "translation": "matina (alusivo a una fiesta matutina)",
    "source_movie": "Taylor Swift The Eras Tour Film",
    "year_processed": "2024",
    "global_frequency": 1
  },
  {
    "id": "v_fdb87f41",
    "word": "We never painted by the numbers",
    "translation": "nunca nos guiado por los número, nunca pintado",
    "source_movie": "Taylor Swift The Eras Tour Film",
    "year_processed": "2024",
    "global_frequency": 1
  },
  {
    "id": "v_6d511b1a",
    "word": "seen lot numerous",
    "translation": "No registrada",
    "source_movie": "Taylor Swift The Eras Tour Film",
    "year_processed": "2024",
    "global_frequency": 1
  },
  {
    "id": "v_c9780322",
    "word": "Flow (verb)",
    "translation": "fluir",
    "source_movie": "Taylor Swift The Eras Tour Film",
    "year_processed": "2024",
    "global_frequency": 1
  },
  {
    "id": "v_eebcaa25",
    "word": "Strumming",
    "translation": "rasgueado",
    "source_movie": "Taylor Swift The Eras Tour Film",
    "year_processed": "2024",
    "global_frequency": 1
  },
  {
    "id": "v_4a3427c6",
    "word": "Woodsy",
    "translation": "boscoso",
    "source_movie": "Taylor Swift The Eras Tour Film",
    "year_processed": "2024",
    "global_frequency": 2
  },
  {
    "id": "v_9dc4cd1b",
    "word": "A candlestick holder-thing",
    "translation": "un portavelas, un candelabro",
    "source_movie": "Taylor Swift The Eras Tour Film",
    "year_processed": "2024",
    "global_frequency": 1
  },
  {
    "id": "v_7029a33e",
    "word": "Parchment paper",
    "translation": "papel vegetal, papel de pergamino",
    "source_movie": "Taylor Swift The Eras Tour Film",
    "year_processed": "2024",
    "global_frequency": 1
  },
  {
    "id": "v_2fba4138",
    "word": "The catalyst character",
    "translation": "el personaje catalizador",
    "source_movie": "Taylor Swift The Eras Tour Film",
    "year_processed": "2024",
    "global_frequency": 1
  },
  {
    "id": "v_722c145f",
    "word": "Screw up",
    "translation": "arruinar, estropear",
    "source_movie": "Taylor Swift The Eras Tour Film",
    "year_processed": "2024",
    "global_frequency": 2
  },
  {
    "id": "v_486e909d",
    "word": "Assumptions",
    "translation": "suposiciones",
    "source_movie": "Taylor Swift The Eras Tour Film",
    "year_processed": "2024",
    "global_frequency": 1
  },
  {
    "id": "v_8b4abdf6",
    "word": "Homeroom",
    "translation": "aula, clase",
    "source_movie": "Taylor Swift The Eras Tour Film",
    "year_processed": "2024",
    "global_frequency": 2
  },
  {
    "id": "v_c883aa3f",
    "word": "I was nowhere to be found",
    "translation": "yo no estafa en ninguna parte",
    "source_movie": "Taylor Swift The Eras Tour Film",
    "year_processed": "2024",
    "global_frequency": 1
  },
  {
    "id": "v_640a14f3",
    "word": "Broken cobblestones",
    "translation": "adoquinar roto, adoquinar quebrado",
    "source_movie": "Taylor Swift The Eras Tour Film",
    "year_processed": "2024",
    "global_frequency": 1
  },
  {
    "id": "v_407c0255",
    "word": "Just thinking of you when she pulled up",
    "translation": "sólo pensada en ti cuando se desuso",
    "source_movie": "Taylor Swift The Eras Tour Film",
    "year_processed": "2024",
    "global_frequency": 1
  },
  {
    "id": "v_84b97138",
    "word": "Figment",
    "translation": "producto, invención",
    "source_movie": "Taylor Swift The Eras Tour Film",
    "year_processed": "2024",
    "global_frequency": 2
  },
  {
    "id": "v_1be003be",
    "word": "Doorstep",
    "translation": "puerta",
    "source_movie": "Taylor Swift The Eras Tour Film",
    "year_processed": "2024",
    "global_frequency": 2
  },
  {
    "id": "v_774fa105",
    "word": "Plan out",
    "translation": "planear",
    "source_movie": "Taylor Swift The Eras Tour Film",
    "year_processed": "2024",
    "global_frequency": 2
  },
  {
    "id": "v_f11f3a59",
    "word": "To make it up to you",
    "translation": "compensártelo",
    "source_movie": "Taylor Swift The Eras Tour Film",
    "year_processed": "2024",
    "global_frequency": 1
  },
  {
    "id": "v_b0dfb39a",
    "word": "Porch",
    "translation": "porche",
    "source_movie": "Taylor Swift The Eras Tour Film",
    "year_processed": "2024",
    "global_frequency": 1
  },
  {
    "id": "v_2e8f0ab2",
    "word": "Streetlight",
    "translation": "farola",
    "source_movie": "Taylor Swift The Eras Tour Film",
    "year_processed": "2024",
    "global_frequency": 2
  },
  {
    "id": "v_3813821c",
    "word": "Ride up",
    "translation": "subir (a un tren)",
    "source_movie": "Taylor Swift The Eras Tour Film",
    "year_processed": "2024",
    "global_frequency": 2
  },
  {
    "id": "v_b4bc0d77",
    "word": "Gauche",
    "translation": "desmañado",
    "source_movie": "Taylor Swift The Eras Tour Film",
    "year_processed": "2024",
    "global_frequency": 1
  },
  {
    "id": "v_2770c9c9",
    "word": "Tasteful",
    "translation": "de buen gusto",
    "source_movie": "Taylor Swift The Eras Tour Film",
    "year_processed": "2024",
    "global_frequency": 2
  },
  {
    "id": "v_c24d6441",
    "word": "Settle down",
    "translation": "calmar, tranqulizarse",
    "source_movie": "Taylor Swift The Eras Tour Film",
    "year_processed": "2024",
    "global_frequency": 5
  },
  {
    "id": "v_ea4e448f",
    "word": "Pacing the rocks",
    "translation": "examinando por las roca",
    "source_movie": "Taylor Swift The Eras Tour Film",
    "year_processed": "2024",
    "global_frequency": 2
  },
  {
    "id": "v_2009d4f3",
    "word": "Stare out",
    "translation": "mirar",
    "source_movie": "Taylor Swift The Eras Tour Film",
    "year_processed": "2024",
    "global_frequency": 1
  },
  {
    "id": "v_f01798d5",
    "word": "Feud",
    "translation": "disputa, enemistad",
    "source_movie": "Taylor Swift The Eras Tour Film",
    "year_processed": "2024",
    "global_frequency": 3
  },
  {
    "id": "v_18315719",
    "word": "And dyed it key lime green",
    "translation": "y lo teña de verde lima",
    "source_movie": "Taylor Swift The Eras Tour Film",
    "year_processed": "2024",
    "global_frequency": 1
  },
  {
    "id": "v_133dcf51",
    "word": "August slipped away into a moment in time",
    "translation": "agosto se transformar en un momento en el",
    "source_movie": "Taylor Swift The Eras Tour Film",
    "year_processed": "2024",
    "global_frequency": 2
  },
  {
    "id": "v_834d0507",
    "word": "tempo",
    "translation": "No registrada",
    "source_movie": "Taylor Swift The Eras Tour Film",
    "year_processed": "2024",
    "global_frequency": 4
  },
  {
    "id": "v_2ef32245",
    "word": "Twisted in bedsheets",
    "translation": "retorcido en sábana, enredador en sábana",
    "source_movie": "Taylor Swift The Eras Tour Film",
    "year_processed": "2024",
    "global_frequency": 1
  },
  {
    "id": "v_302c543a",
    "word": "August sipped away like a bottle of wine",
    "translation": "agosto se disgusto como una botella de vino",
    "source_movie": "Taylor Swift The Eras Tour Film",
    "year_processed": "2024",
    "global_frequency": 2
  },
  {
    "id": "v_414868a1",
    "word": "Beneath the sun",
    "translation": "bajo el sol",
    "source_movie": "Taylor Swift The Eras Tour Film",
    "year_processed": "2024",
    "global_frequency": 1
  },
  {
    "id": "v_686e6b0d",
    "word": "For the hope of it all",
    "translation": "por la esperanza de todo",
    "source_movie": "Taylor Swift The Eras Tour Film",
    "year_processed": "2024",
    "global_frequency": 1
  },
  {
    "id": "v_d37d45a6",
    "word": "This godforsaken mess",
    "translation": "este odio desastre",
    "source_movie": "Taylor Swift The Eras Tour Film",
    "year_processed": "2024",
    "global_frequency": 1
  },
  {
    "id": "v_b3e251e4",
    "word": "Sunlit room",
    "translation": "habitación iluminada por el sol",
    "source_movie": "Taylor Swift The Eras Tour Film",
    "year_processed": "2024",
    "global_frequency": 2
  },
  {
    "id": "v_6436fd91",
    "word": "My tears ricochet",
    "translation": "mis lágrima rebotar",
    "source_movie": "Taylor Swift The Eras Tour Film",
    "year_processed": "2024",
    "global_frequency": 1
  },
  {
    "id": "v_5ff94ae9",
    "word": "Haunt (verb)",
    "translation": "perseguir, atormentar",
    "source_movie": "Taylor Swift The Eras Tour Film",
    "year_processed": "2024",
    "global_frequency": 4
  },
  {
    "id": "v_eee97850",
    "word": "Lullabies",
    "translation": "cancionero de cuna",
    "source_movie": "Taylor Swift The Eras Tour Film",
    "year_processed": "2024",
    "global_frequency": 1
  },
  {
    "id": "v_1331c89a",
    "word": "You’re tossing out blame",
    "translation": "estas echado la culpa",
    "source_movie": "Taylor Swift The Eras Tour Film",
    "year_processed": "2024",
    "global_frequency": 1
  },
  {
    "id": "v_e367fbc6",
    "word": "Cross out",
    "translation": "tachar",
    "source_movie": "Taylor Swift The Eras Tour Film",
    "year_processed": "2024",
    "global_frequency": 1
  },
  {
    "id": "v_07c048cb",
    "word": "Vintage tee",
    "translation": "camiseta vinagre",
    "source_movie": "Taylor Swift The Eras Tour Film",
    "year_processed": "2024",
    "global_frequency": 1
  },
  {
    "id": "v_dfbe8163",
    "word": "Cobblestones",
    "translation": "adoquinar",
    "source_movie": "Taylor Swift The Eras Tour Film",
    "year_processed": "2024",
    "global_frequency": 1
  },
  {
    "id": "v_10ac7fe1",
    "word": "Sequin smile",
    "translation": "sonrisa de lentejuela",
    "source_movie": "Taylor Swift The Eras Tour Film",
    "year_processed": "2024",
    "global_frequency": 2
  },
  {
    "id": "v_f76f1595",
    "word": "Sweatshirt",
    "translation": "sudadera, poltrón",
    "source_movie": "Taylor Swift The Eras Tour Film",
    "year_processed": "2024",
    "global_frequency": 2
  },
  {
    "id": "v_11832d35",
    "word": "Bloodstain",
    "translation": "mancha de sangre",
    "source_movie": "Taylor Swift The Eras Tour Film",
    "year_processed": "2024",
    "global_frequency": 1
  },
  {
    "id": "v_b49d5ae8",
    "word": "Linger (verb)",
    "translation": "quedar",
    "source_movie": "Taylor Swift The Eras Tour Film",
    "year_processed": "2024",
    "global_frequency": 4
  },
  {
    "id": "v_f60b75f6",
    "word": "What-ifs",
    "translation": "y si",
    "source_movie": "Taylor Swift The Eras Tour Film",
    "year_processed": "2024",
    "global_frequency": 1
  },
  {
    "id": "v_06b1a059",
    "word": "Hang around",
    "translation": "quedar (de permanecer por un tiempo)",
    "source_movie": "Taylor Swift The Eras Tour Film",
    "year_processed": "2024",
    "global_frequency": 6
  },
  {
    "id": "v_13a8d80b",
    "word": "The grocery line",
    "translation": "la cola del supermercado",
    "source_movie": "Taylor Swift The Eras Tour Film",
    "year_processed": "2024",
    "global_frequency": 1
  },
  {
    "id": "v_16c9e4d6",
    "word": "My front porch light",
    "translation": "la luz de mi porche delantero",
    "source_movie": "Taylor Swift The Eras Tour Film",
    "year_processed": "2024",
    "global_frequency": 1
  },
  {
    "id": "v_2abf9823",
    "word": "Headlights",
    "translation": "faro",
    "source_movie": "Taylor Swift The Eras Tour Film",
    "year_processed": "2024",
    "global_frequency": 2
  },
  {
    "id": "v_9143c689",
    "word": "Burning flames",
    "translation": "llama ardiente",
    "source_movie": "Taylor Swift The Eras Tour Film",
    "year_processed": "2024",
    "global_frequency": 1
  },
  {
    "id": "v_99d93cb4",
    "word": "Fade into view",
    "translation": "desaparecer a la vista",
    "source_movie": "Taylor Swift The Eras Tour Film",
    "year_processed": "2024",
    "global_frequency": 1
  },
  {
    "id": "v_0c07d4bd",
    "word": "Crash down",
    "translation": "estrellar, derrumbar",
    "source_movie": "Taylor Swift The Eras Tour Film",
    "year_processed": "2024",
    "global_frequency": 2
  },
  {
    "id": "v_204eb238",
    "word": "Slicked back",
    "translation": "espalda al aire",
    "source_movie": "Taylor Swift The Eras Tour Film",
    "year_processed": "2024",
    "global_frequency": 1
  },
  {
    "id": "v_f94fb72f",
    "word": "It’s gonna go down in flames",
    "translation": "va a caer en llama",
    "source_movie": "Taylor Swift The Eras Tour Film",
    "year_processed": "2024",
    "global_frequency": 1
  },
  {
    "id": "v_08bdd767",
    "word": "If the high was worth the pain",
    "translation": "si el subido salir la pena",
    "source_movie": "Taylor Swift The Eras Tour Film",
    "year_processed": "2024",
    "global_frequency": 2
  },
  {
    "id": "v_f4c279bb",
    "word": "We’re reckless",
    "translation": "somo imprudente, somo temerario",
    "source_movie": "Taylor Swift The Eras Tour Film",
    "year_processed": "2024",
    "global_frequency": 1
  },
  {
    "id": "v_9831d2ec",
    "word": "We’ll take this way too far",
    "translation": "llevaremos esto demasiado lejos",
    "source_movie": "Taylor Swift The Eras Tour Film",
    "year_processed": "2024",
    "global_frequency": 1
  },
  {
    "id": "v_429a48d0",
    "word": "Breathless",
    "translation": "sin aliento",
    "source_movie": "Taylor Swift The Eras Tour Film",
    "year_processed": "2024",
    "global_frequency": 1
  },
  {
    "id": "v_c27f73d7",
    "word": "Cherry lips",
    "translation": "labio de cereza",
    "source_movie": "Taylor Swift The Eras Tour Film",
    "year_processed": "2024",
    "global_frequency": 2
  },
  {
    "id": "v_d1bdfd6d",
    "word": "Second-guess (verb)",
    "translation": "cuestionar, dudar",
    "source_movie": "Taylor Swift The Eras Tour Film",
    "year_processed": "2024",
    "global_frequency": 1
  },
  {
    "id": "v_2949dfbe",
    "word": "Jealousy",
    "translation": "celoso",
    "source_movie": "Taylor Swift The Eras Tour Film",
    "year_processed": "2024",
    "global_frequency": 1
  },
  {
    "id": "v_dee04485",
    "word": "I go on too many dates",
    "translation": "hoy a demasiada cita",
    "source_movie": "Taylor Swift The Eras Tour Film",
    "year_processed": "2024",
    "global_frequency": 1
  },
  {
    "id": "v_0104ce93",
    "word": "Heart-breakers",
    "translation": "rompecorazones",
    "source_movie": "Taylor Swift The Eras Tour Film",
    "year_processed": "2024",
    "global_frequency": 1
  },
  {
    "id": "v_b8b9dd90",
    "word": "Fakers",
    "translation": "farsante",
    "source_movie": "Taylor Swift The Eras Tour Film",
    "year_processed": "2024",
    "global_frequency": 2
  },
  {
    "id": "v_0a54504b",
    "word": "I never miss a beat",
    "translation": "nunca pierio el ritmo",
    "source_movie": "Taylor Swift The Eras Tour Film",
    "year_processed": "2024",
    "global_frequency": 1
  },
  {
    "id": "v_f6c68109",
    "word": "I’m lightning",
    "translation": "son un rayo",
    "source_movie": "Taylor Swift The Eras Tour Film",
    "year_processed": "2024",
    "global_frequency": 1
  },
  {
    "id": "v_a57440da",
    "word": "I make the moves up as I go",
    "translation": "pago los movimiento sobre la marcha",
    "source_movie": "Taylor Swift The Eras Tour Film",
    "year_processed": "2024",
    "global_frequency": 1
  },
  {
    "id": "v_def379c0",
    "word": "While you’ve been getting down and out",
    "translation": "mientras las estado deprimir",
    "source_movie": "Taylor Swift The Eras Tour Film",
    "year_processed": "2024",
    "global_frequency": 1
  },
  {
    "id": "v_8453360b",
    "word": "riot inferno",
    "translation": "No registrada",
    "source_movie": "Taylor Swift The Eras Tour Film",
    "year_processed": "2024",
    "global_frequency": 1
  },
  {
    "id": "v_39006993",
    "word": "With the hell good hair",
    "translation": "con el pelo tan bueno",
    "source_movie": "Taylor Swift The Eras Tour Film",
    "year_processed": "2024",
    "global_frequency": 1
  },
  {
    "id": "v_44cfa7cf",
    "word": "Come on over",
    "translation": "venir",
    "source_movie": "Taylor Swift The Eras Tour Film",
    "year_processed": "2024",
    "global_frequency": 2
  },
  {
    "id": "v_ff6d946c",
    "word": "Mad love",
    "translation": "amor loco",
    "source_movie": "Taylor Swift The Eras Tour Film",
    "year_processed": "2024",
    "global_frequency": 1
  },
  {
    "id": "v_43fa72d0",
    "word": "A really deep cut",
    "translation": "un corte realmente profundo",
    "source_movie": "Taylor Swift The Eras Tour Film",
    "year_processed": "2024",
    "global_frequency": 1
  },
  {
    "id": "v_9afe2e44",
    "word": "Hindsight",
    "translation": "a posterior, en retrospectiva",
    "source_movie": "Taylor Swift The Eras Tour Film",
    "year_processed": "2024",
    "global_frequency": 1
  },
  {
    "id": "v_f985621e",
    "word": "Burning it down",
    "translation": "quemándolo",
    "source_movie": "Taylor Swift The Eras Tour Film",
    "year_processed": "2024",
    "global_frequency": 1
  },
  {
    "id": "v_3a024892",
    "word": "Music droning",
    "translation": "música zumbido",
    "source_movie": "Taylor Swift The Eras Tour Film",
    "year_processed": "2024",
    "global_frequency": 1
  },
  {
    "id": "v_9cffd06b",
    "word": "The slamming screen door",
    "translation": "una puerta de tela mecánica que se tierra de golpe",
    "source_movie": "Taylor Swift The Eras Tour Film",
    "year_processed": "2024",
    "global_frequency": 1
  },
  {
    "id": "v_9a4c9cd2",
    "word": "Sneak out",
    "translation": "descabullirse",
    "source_movie": "Taylor Swift The Eras Tour Film",
    "year_processed": "2024",
    "global_frequency": 3
  },
  {
    "id": "v_cf828c6a",
    "word": "Tapping on your window",
    "translation": "golpeado en su ventana",
    "source_movie": "Taylor Swift The Eras Tour Film",
    "year_processed": "2024",
    "global_frequency": 1
  },
  {
    "id": "v_ba0134c6",
    "word": "The front porch steps",
    "translation": "los escalonar del porche delantero",
    "source_movie": "Taylor Swift The Eras Tour Film",
    "year_processed": "2024",
    "global_frequency": 1
  },
  {
    "id": "v_09e55d8e",
    "word": "It had been trample on",
    "translation": "habla sino picoteado",
    "source_movie": "Taylor Swift The Eras Tour Film",
    "year_processed": "2024",
    "global_frequency": 1
  },
  {
    "id": "v_ba46e86b",
    "word": "Come along",
    "translation": "llegar algo, aparecer algo",
    "source_movie": "Taylor Swift The Eras Tour Film",
    "year_processed": "2024",
    "global_frequency": 8
  },
  {
    "id": "v_dc7965bc",
    "word": "Napkin",
    "translation": "servilleta",
    "source_movie": "Taylor Swift The Eras Tour Film",
    "year_processed": "2024",
    "global_frequency": 2
  },
  {
    "id": "v_a5a172a6",
    "word": "Yearning (substantive)",
    "translation": "anhelo",
    "source_movie": "Taylor Swift The Eras Tour Film",
    "year_processed": "2024",
    "global_frequency": 1
  },
  {
    "id": "v_a0c881fd",
    "word": "I play it cool",
    "translation": "juego bien",
    "source_movie": "Taylor Swift The Eras Tour Film",
    "year_processed": "2024",
    "global_frequency": 1
  },
  {
    "id": "v_a05bcf3b",
    "word": "Sprinkler splashes",
    "translation": "salpicadura de aspersorio",
    "source_movie": "Taylor Swift The Eras Tour Film",
    "year_processed": "2024",
    "global_frequency": 1
  },
  {
    "id": "v_1bcd3f2b",
    "word": "Fireplace ashes",
    "translation": "ceniza de chimenea",
    "source_movie": "Taylor Swift The Eras Tour Film",
    "year_processed": "2024",
    "global_frequency": 1
  },
  {
    "id": "v_ee910c3f",
    "word": "Something different bloomed",
    "translation": "algo diferente florecer",
    "source_movie": "Taylor Swift The Eras Tour Film",
    "year_processed": "2024",
    "global_frequency": 1
  },
  {
    "id": "v_4ba92eec",
    "word": "And I starved my body",
    "translation": "y mate de hambre a mi cuerpo",
    "source_movie": "Taylor Swift The Eras Tour Film",
    "year_processed": "2024",
    "global_frequency": 1
  },
  {
    "id": "v_c33d8f77",
    "word": "A blood-soaked gown",
    "translation": "un vestido empañado de sangre",
    "source_movie": "Taylor Swift The Eras Tour Film",
    "year_processed": "2024",
    "global_frequency": 1
  },
  {
    "id": "v_4478a7dc",
    "word": "Take away",
    "translation": "quitar",
    "source_movie": "Taylor Swift The Eras Tour Film",
    "year_processed": "2024",
    "global_frequency": 2
  },
  {
    "id": "v_fbfa8568",
    "word": "There were pages turned",
    "translation": "hablar página pasada",
    "source_movie": "Taylor Swift The Eras Tour Film",
    "year_processed": "2024",
    "global_frequency": 1
  },
  {
    "id": "v_a3ecaf84",
    "word": "Water bubbling",
    "translation": "burbujeo de agua",
    "source_movie": "Taylor Swift The Eras Tour Film",
    "year_processed": "2024",
    "global_frequency": 1
  },
  {
    "id": "v_8e30a793",
    "word": "Water splashes",
    "translation": "salpicadura de agua",
    "source_movie": "Taylor Swift The Eras Tour Film",
    "year_processed": "2024",
    "global_frequency": 1
  },
  {
    "id": "v_414217f6",
    "word": "Loud cheering",
    "translation": "vitorear ruidoso",
    "source_movie": "Taylor Swift The Eras Tour Film",
    "year_processed": "2024",
    "global_frequency": 1
  },
  {
    "id": "v_db216189",
    "word": "Muffled water rumbling",
    "translation": "estruendo sordo de agua",
    "source_movie": "Taylor Swift The Eras Tour Film",
    "year_processed": "2024",
    "global_frequency": 1
  },
  {
    "id": "v_9ac3e7cd",
    "word": "Lavender haze",
    "translation": "bruma de lavada",
    "source_movie": "Taylor Swift The Eras Tour Film",
    "year_processed": "2024",
    "global_frequency": 1
  },
  {
    "id": "v_61d4f489",
    "word": "Staring at the ceiling",
    "translation": "mirado al techo",
    "source_movie": "Taylor Swift The Eras Tour Film",
    "year_processed": "2024",
    "global_frequency": 1
  },
  {
    "id": "v_a804de6c",
    "word": "It’s creeping up on me",
    "translation": "me esta invadiente",
    "source_movie": "Taylor Swift The Eras Tour Film",
    "year_processed": "2024",
    "global_frequency": 1
  },
  {
    "id": "v_eaedd1cd",
    "word": "Talk your talk",
    "translation": "habla como fueras",
    "source_movie": "Taylor Swift The Eras Tour Film",
    "year_processed": "2024",
    "global_frequency": 1
  },
  {
    "id": "v_42032315",
    "word": "Get it off your chest",
    "translation": "desahógate, quítatelo de encima",
    "source_movie": "Taylor Swift The Eras Tour Film",
    "year_processed": "2024",
    "global_frequency": 1
  },
  {
    "id": "v_5cfdf200",
    "word": "When my depression works the graveyard shift",
    "translation": "cuando mi depresión trabajo en el",
    "source_movie": "Taylor Swift The Eras Tour Film",
    "year_processed": "2024",
    "global_frequency": 1
  },
  {
    "id": "v_3ea4930d",
    "word": "turn de niche",
    "translation": "No registrada",
    "source_movie": "Taylor Swift The Eras Tour Film",
    "year_processed": "2024",
    "global_frequency": 1
  },
  {
    "id": "v_9c0eff4c",
    "word": "Vices",
    "translation": "vicio",
    "source_movie": "Taylor Swift The Eras Tour Film",
    "year_processed": "2024",
    "global_frequency": 1
  },
  {
    "id": "v_efd96781",
    "word": "Tale as old as time",
    "translation": "un cuento tan antiguo como el tiempo",
    "source_movie": "Taylor Swift The Eras Tour Film",
    "year_processed": "2024",
    "global_frequency": 1
  },
  {
    "id": "v_b02ede28",
    "word": "You got tired of my scheming",
    "translation": "te cantante de mis intriga",
    "source_movie": "Taylor Swift The Eras Tour Film",
    "year_processed": "2024",
    "global_frequency": 1
  },
  {
    "id": "v_0faf6439",
    "word": "Stare (verb)",
    "translation": "mirar (fijamente)",
    "source_movie": "Taylor Swift The Eras Tour Film",
    "year_processed": "2024",
    "global_frequency": 2
  },
  {
    "id": "v_c5a619ce",
    "word": "Rooting for the anti-hero",
    "translation": "apoyar al antiaéreo",
    "source_movie": "Taylor Swift The Eras Tour Film",
    "year_processed": "2024",
    "global_frequency": 1
  },
  {
    "id": "v_193ac46f",
    "word": "Slowly lurching toward your favorite city",
    "translation": "avanzado lentamente hacia tu ciudad",
    "source_movie": "Taylor Swift The Eras Tour Film",
    "year_processed": "2024",
    "global_frequency": 1
  },
  {
    "id": "v_d84ed9d2",
    "word": "favorite",
    "translation": "No registrada",
    "source_movie": "Taylor Swift The Eras Tour Film",
    "year_processed": "2024",
    "global_frequency": 1
  },
  {
    "id": "v_e5ab9a13",
    "word": "Pierced through the heart",
    "translation": "atravesado por el corazón",
    "source_movie": "Taylor Swift The Eras Tour Film",
    "year_processed": "2024",
    "global_frequency": 1
  },
  {
    "id": "v_6a238276",
    "word": "My covert narcissism",
    "translation": "mi narcisismo encubierto",
    "source_movie": "Taylor Swift The Eras Tour Film",
    "year_processed": "2024",
    "global_frequency": 1
  },
  {
    "id": "v_446b33d0",
    "word": "Disguise (verb)",
    "translation": "disfrezarse",
    "source_movie": "Taylor Swift The Eras Tour Film",
    "year_processed": "2024",
    "global_frequency": 2
  },
  {
    "id": "v_469d9564",
    "word": "Scream out",
    "translation": "gritar",
    "source_movie": "Taylor Swift The Eras Tour Film",
    "year_processed": "2024",
    "global_frequency": 1
  },
  {
    "id": "v_5e474001",
    "word": "Wasteland",
    "translation": "páramo, erial, terreno baldío",
    "source_movie": "Taylor Swift The Eras Tour Film",
    "year_processed": "2024",
    "global_frequency": 2
  },
  {
    "id": "v_bbfab8ad",
    "word": "Pageant queens",
    "translation": "reina de concurso",
    "source_movie": "Taylor Swift The Eras Tour Film",
    "year_processed": "2024",
    "global_frequency": 1
  },
  {
    "id": "v_c23f744c",
    "word": "A slow motion, love potion",
    "translation": "una poción de amor a cámara lenta",
    "source_movie": "Taylor Swift The Eras Tour Film",
    "year_processed": "2024",
    "global_frequency": 1
  },
  {
    "id": "v_0dc59987",
    "word": "Jump off",
    "translation": "saltar",
    "source_movie": "Taylor Swift The Eras Tour Film",
    "year_processed": "2024",
    "global_frequency": 2
  },
  {
    "id": "v_10eb2723",
    "word": "He was sunshine",
    "translation": "él era un sol",
    "source_movie": "Taylor Swift The Eras Tour Film",
    "year_processed": "2024",
    "global_frequency": 1
  },
  {
    "id": "v_e934b32f",
    "word": "Holiday peppermint candy",
    "translation": "dulce de menta navideño",
    "source_movie": "Taylor Swift The Eras Tour Film",
    "year_processed": "2024",
    "global_frequency": 1
  },
  {
    "id": "v_871cb281",
    "word": "Peer (verb)",
    "translation": "asomar, mirar (por una ventana)",
    "source_movie": "Taylor Swift The Eras Tour Film",
    "year_processed": "2024",
    "global_frequency": 1
  },
  {
    "id": "v_fee25199",
    "word": "Unravel (verb)",
    "translation": "desentrañar, desvelar, desenredar",
    "source_movie": "Taylor Swift The Eras Tour Film",
    "year_processed": "2024",
    "global_frequency": 2
  },
  {
    "id": "v_aa230719",
    "word": "Some kind of haunted",
    "translation": "algún tipo de brujo",
    "source_movie": "Taylor Swift The Eras Tour Film",
    "year_processed": "2024",
    "global_frequency": 1
  },
  {
    "id": "v_1483829a",
    "word": "Sharp enough",
    "translation": "suficientemente afilador",
    "source_movie": "Taylor Swift The Eras Tour Film",
    "year_processed": "2024",
    "global_frequency": 1
  },
  {
    "id": "v_b27efdad",
    "word": "Get even",
    "translation": "véngate",
    "source_movie": "Taylor Swift The Eras Tour Film",
    "year_processed": "2024",
    "global_frequency": 1
  },
  {
    "id": "v_94b458b3",
    "word": "Envelope",
    "translation": "sobre",
    "source_movie": "Taylor Swift The Eras Tour Film",
    "year_processed": "2024",
    "global_frequency": 1
  },
  {
    "id": "v_0e85637b",
    "word": "Picture me thick as thieves",
    "translation": "imagíname miedo uña y carne",
    "source_movie": "Taylor Swift The Eras Tour Film",
    "year_processed": "2024",
    "global_frequency": 1
  },
  {
    "id": "v_c81bfdde",
    "word": "estes pisoteando mi tranquilized",
    "translation": "No registrada",
    "source_movie": "Taylor Swift The Eras Tour Film",
    "year_processed": "2024",
    "global_frequency": 1
  },
  {
    "id": "v_0bbfa20e",
    "word": "I’m still bejeweled",
    "translation": "todavía esto enjoyado",
    "source_movie": "Taylor Swift The Eras Tour Film",
    "year_processed": "2024",
    "global_frequency": 1
  },
  {
    "id": "v_ac3d32e4",
    "word": "Make shimmer (verb)",
    "translation": "hacer brillar (un lugar)",
    "source_movie": "Taylor Swift The Eras Tour Film",
    "year_processed": "2024",
    "global_frequency": 1
  },
  {
    "id": "v_b440cf00",
    "word": "Familiarity breeds contempt",
    "translation": "la familiaridad general desprecio",
    "source_movie": "Taylor Swift The Eras Tour Film",
    "year_processed": "2024",
    "global_frequency": 1
  },
  {
    "id": "v_d42cd30b",
    "word": "Polish up",
    "translation": "brillar",
    "source_movie": "Taylor Swift The Eras Tour Film",
    "year_processed": "2024",
    "global_frequency": 1
  },
  {
    "id": "v_ce938cc6",
    "word": "Get graded",
    "translation": "calificar",
    "source_movie": "Taylor Swift The Eras Tour Film",
    "year_processed": "2024",
    "global_frequency": 1
  },
  {
    "id": "v_2b652177",
    "word": "I miss sparking",
    "translation": "extraño brillar",
    "source_movie": "Taylor Swift The Eras Tour Film",
    "year_processed": "2024",
    "global_frequency": 1
  },
  {
    "id": "v_e387cd01",
    "word": "Sapphire tears on my face",
    "translation": "lágrima de zafiro en mi rostro",
    "source_movie": "Taylor Swift The Eras Tour Film",
    "year_processed": "2024",
    "global_frequency": 1
  },
  {
    "id": "v_2ff3e794",
    "word": "My aura’s moonstone",
    "translation": "la piedra lunar de mi aura",
    "source_movie": "Taylor Swift The Eras Tour Film",
    "year_processed": "2024",
    "global_frequency": 1
  },
  {
    "id": "v_af413a86",
    "word": "Lit the fuse",
    "translation": "incendio la mecha",
    "source_movie": "Taylor Swift The Eras Tour Film",
    "year_processed": "2024",
    "global_frequency": 1
  },
  {
    "id": "v_f6b48c7b",
    "word": "Countermoves",
    "translation": "contraataque",
    "source_movie": "Taylor Swift The Eras Tour Film",
    "year_processed": "2024",
    "global_frequency": 1
  },
  {
    "id": "v_8c6ba7ac",
    "word": "Assess (verb)",
    "translation": "evaluar",
    "source_movie": "Taylor Swift The Eras Tour Film",
    "year_processed": "2024",
    "global_frequency": 2
  },
  {
    "id": "v_9d6aaead",
    "word": "I laid the groundwork",
    "translation": "pues los cimiento",
    "source_movie": "Taylor Swift The Eras Tour Film",
    "year_processed": "2024",
    "global_frequency": 1
  },
  {
    "id": "v_5015a36b",
    "word": "Clockwork",
    "translation": "reloj",
    "source_movie": "Taylor Swift The Eras Tour Film",
    "year_processed": "2024",
    "global_frequency": 2
  },
  {
    "id": "v_61e7503c",
    "word": "The dominoes cascaded in a line",
    "translation": "las ficha de dominó se alinear en cascada",
    "source_movie": "Taylor Swift The Eras Tour Film",
    "year_processed": "2024",
    "global_frequency": 1
  },
  {
    "id": "v_70c0ff36",
    "word": "The pawn",
    "translation": "el peón",
    "source_movie": "Taylor Swift The Eras Tour Film",
    "year_processed": "2024",
    "global_frequency": 1
  },
  {
    "id": "v_bd7f45df",
    "word": "Free-flowing sails",
    "translation": "velero que flujo libremente",
    "source_movie": "Taylor Swift The Eras Tour Film",
    "year_processed": "2024",
    "global_frequency": 1
  },
  {
    "id": "v_330dc0cf",
    "word": "Scheme (verb)",
    "translation": "maquinar, tramar, planear",
    "source_movie": "Taylor Swift The Eras Tour Film",
    "year_processed": "2024",
    "global_frequency": 1
  },
  {
    "id": "v_d3e8323f",
    "word": "And make it seem effortless",
    "translation": "y hacer que pareja sin esfuerzo",
    "source_movie": "Taylor Swift The Eras Tour Film",
    "year_processed": "2024",
    "global_frequency": 1
  },
  {
    "id": "v_ab796450",
    "word": "A wide smirk",
    "translation": "una amplia sonrisa",
    "source_movie": "Taylor Swift The Eras Tour Film",
    "year_processed": "2024",
    "global_frequency": 1
  },
  {
    "id": "v_140aaaa9",
    "word": "su tempo, el equivalent a una cancan?",
    "translation": "No registrada",
    "source_movie": "Taylor Swift The Eras Tour Film",
    "year_processed": "2024",
    "global_frequency": 1
  },
  {
    "id": "v_e1e94f7c",
    "word": "Glare",
    "translation": "brillo, resplandor",
    "source_movie": "Taylor Swift The Eras Tour Film",
    "year_processed": "2024",
    "global_frequency": 1
  },
  {
    "id": "v_e1e69405",
    "word": "Karma is the breeze",
    "translation": "el arma es la brisa",
    "source_movie": "Taylor Swift The Eras Tour Film",
    "year_processed": "2024",
    "global_frequency": 1
  },
  {
    "id": "v_b5d0b53e",
    "word": "Purring in my lap",
    "translation": "ronroneando en mi regazo",
    "source_movie": "Taylor Swift The Eras Tour Film",
    "year_processed": "2024",
    "global_frequency": 1
  },
  {
    "id": "v_69e8a7db",
    "word": "Flex (verb)",
    "translation": "flexional",
    "source_movie": "Taylor Swift The Eras Tour Film",
    "year_processed": "2024",
    "global_frequency": 1
  },
  {
    "id": "v_28f4fc82",
    "word": "Weave your little webs of opacity",
    "translation": "eje tus pequeña telaraña de opacidad",
    "source_movie": "Taylor Swift The Eras Tour Film",
    "year_processed": "2024",
    "global_frequency": 1
  },
  {
    "id": "v_1f9c0baf",
    "word": "Trick (verb)",
    "translation": "engañar",
    "source_movie": "Taylor Swift The Eras Tour Film",
    "year_processed": "2024",
    "global_frequency": 2
  },
  {
    "id": "v_62c8caf0",
    "word": "It’s coming back around",
    "translation": "esta volviendo",
    "source_movie": "Taylor Swift The Eras Tour Film",
    "year_processed": "2024",
    "global_frequency": 1
  },
  {
    "id": "v_5810c156",
    "word": "Rattling your ground",
    "translation": "sacudido tu suelo",
    "source_movie": "Taylor Swift The Eras Tour Film",
    "year_processed": "2024",
    "global_frequency": 1
  },
  {
    "id": "v_68d0ef00",
    "word": "Scent",
    "translation": "aroma, olor",
    "source_movie": "Taylor Swift The Eras Tour Film",
    "year_processed": "2024",
    "global_frequency": 2
  },
  {
    "id": "v_c5ef25e7",
    "word": "Track down",
    "translation": "seguir, rastrear",
    "source_movie": "Taylor Swift The Eras Tour Film",
    "year_processed": "2024",
    "global_frequency": 3
  },
  {
    "id": "v_771dab56",
    "word": "Summit",
    "translation": "cumbre, cima",
    "source_movie": "Taylor Swift The Eras Tour Film",
    "year_processed": "2024",
    "global_frequency": 2
  },
  {
    "id": "v_25f18362",
    "word": "Band sustaining outdo",
    "translation": "otro sostenido por la banda",
    "source_movie": "Taylor Swift The Eras Tour Film",
    "year_processed": "2024",
    "global_frequency": 1
  },
  {
    "id": "v_9569406b",
    "word": "I ride off alone",
    "translation": "me hoy sola",
    "source_movie": "Taylor Swift The Eras Tour Film",
    "year_processed": "2024",
    "global_frequency": 3
  },
  {
    "id": "v_5e65ca7e",
    "word": "Hold onto you",
    "translation": "arrate a ti, arrate a ti",
    "source_movie": "Taylor Swift The Eras Tour Film",
    "year_processed": "2024",
    "global_frequency": 1
  },
  {
    "id": "v_1dfc3415",
    "word": "Upbeat music playing",
    "translation": "buena música alegre",
    "source_movie": "Taylor Swift The Eras Tour Film",
    "year_processed": "2024",
    "global_frequency": 1
  },
  {
    "id": "v_5b91ad56",
    "word": "Rosy cheeks",
    "translation": "mejilla rosada",
    "source_movie": "Taylor Swift The Eras Tour Film",
    "year_processed": "2024",
    "global_frequency": 2
  },
  {
    "id": "v_3c4bd48b",
    "word": "avocado en casa face de mi carreras",
    "translation": "No registrada",
    "source_movie": "Taylor Swift The Eras Tour Film",
    "year_processed": "2024",
    "global_frequency": 1
  },
  {
    "id": "v_3a643166",
    "word": "You brush past me in the hallway",
    "translation": "me roza en el pasillo",
    "source_movie": "Taylor Swift The Eras Tour Film",
    "year_processed": "2024",
    "global_frequency": 1
  },
  {
    "id": "v_a8b144ef",
    "word": "They keep watchful eyes on us",
    "translation": "ellos nos vigilar",
    "source_movie": "Taylor Swift The Eras Tour Film",
    "year_processed": "2024",
    "global_frequency": 1
  },
  {
    "id": "v_5e5a8041",
    "word": "Necktie",
    "translation": "corbata",
    "source_movie": "Taylor Swift The Eras Tour Film",
    "year_processed": "2024",
    "global_frequency": 1
  },
  {
    "id": "v_8b78ccbd",
    "word": "You should sing it really loudly",
    "translation": "bebería cantarela muy fuerte",
    "source_movie": "Taylor Swift The Eras Tour Film",
    "year_processed": "2024",
    "global_frequency": 1
  },
  {
    "id": "v_6cd16476",
    "word": "Chandelier’s still flickering here",
    "translation": "el candelabro sigua parpadeando aquí",
    "source_movie": "Taylor Swift The Eras Tour Film",
    "year_processed": "2024",
    "global_frequency": 2
  },
  {
    "id": "v_307d001f",
    "word": "A lawless land",
    "translation": "una tierra sin ley",
    "source_movie": "Taylor Swift The Eras Tour Film",
    "year_processed": "2024",
    "global_frequency": 2
  },
  {
    "id": "v_a5d02a12",
    "word": "Paper cut stings from our paper-thin plans",
    "translation": "las cortadura de papel orden a causa de",
    "source_movie": "Taylor Swift The Eras Tour Film",
    "year_processed": "2024",
    "global_frequency": 2
  },
  {
    "id": "v_f9fcbf63",
    "word": "maestros planes fragile como el paper",
    "translation": "No registrada",
    "source_movie": "Taylor Swift The Eras Tour Film",
    "year_processed": "2024",
    "global_frequency": 2
  },
  {
    "id": "v_962675f0",
    "word": "Deafening",
    "translation": "ensordecedor",
    "source_movie": "Taylor Swift The Eras Tour Film",
    "year_processed": "2024",
    "global_frequency": 1
  },
  {
    "id": "v_8d310935",
    "word": "Lighthearted joke",
    "translation": "broma desenfadada",
    "source_movie": "Taylor Swift The Eras Tour Film",
    "year_processed": "2024",
    "global_frequency": 1
  },
  {
    "id": "v_783515c1",
    "word": "Your shoulders brush",
    "translation": "tus hombro roza",
    "source_movie": "Taylor Swift The Eras Tour Film",
    "year_processed": "2024",
    "global_frequency": 1
  },
  {
    "id": "v_9319503c",
    "word": "Burnt toast",
    "translation": "tostada quemada",
    "source_movie": "Taylor Swift The Eras Tour Film",
    "year_processed": "2024",
    "global_frequency": 1
  },
  {
    "id": "v_bc0e9a34",
    "word": "Giggle (verb)",
    "translation": "rearme",
    "source_movie": "Taylor Swift The Eras Tour Film",
    "year_processed": "2024",
    "global_frequency": 5
  },
  {
    "id": "v_31fdbe65",
    "word": "We were cleaning incense",
    "translation": "estábamos limpiador el incienso",
    "source_movie": "Taylor Swift The Eras Tour Film",
    "year_processed": "2024",
    "global_frequency": 1
  },
  {
    "id": "v_1ddeda43",
    "word": "Lap (en reference al curio)",
    "translation": "regazo",
    "source_movie": "Taylor Swift The Eras Tour Film",
    "year_processed": "2024",
    "global_frequency": 1
  },
  {
    "id": "v_dfb92beb",
    "word": "Your roommate’s cheap-ass screw-top rose",
    "translation": "el vino rosado barato de rosca de tu",
    "source_movie": "Taylor Swift The Eras Tour Film",
    "year_processed": "2024",
    "global_frequency": 1
  },
  {
    "id": "v_32609fe7",
    "word": "comparer de quarto",
    "translation": "No registrada",
    "source_movie": "Taylor Swift The Eras Tour Film",
    "year_processed": "2024",
    "global_frequency": 1
  },
  {
    "id": "v_15aa00c4",
    "word": "Burgundy",
    "translation": "borgoña",
    "source_movie": "Taylor Swift The Eras Tour Film",
    "year_processed": "2024",
    "global_frequency": 2
  },
  {
    "id": "v_291c02de",
    "word": "The blood rushed into my cheeks",
    "translation": "la sangre se precipitar en mis mejilla",
    "source_movie": "Taylor Swift The Eras Tour Film",
    "year_processed": "2024",
    "global_frequency": 1
  },
  {
    "id": "v_fbd0b984",
    "word": "Collarbone",
    "translation": "clavícula",
    "source_movie": "Taylor Swift The Eras Tour Film",
    "year_processed": "2024",
    "global_frequency": 1
  },
  {
    "id": "v_e21c4e4d",
    "word": "Hazy",
    "translation": "confuso",
    "source_movie": "Taylor Swift The Eras Tour Film",
    "year_processed": "2024",
    "global_frequency": 1
  },
  {
    "id": "v_a8d2eaf6",
    "word": "You were standing hollow-eyed",
    "translation": "estábamos parado con los ojo hundidor",
    "source_movie": "Taylor Swift The Eras Tour Film",
    "year_processed": "2024",
    "global_frequency": 1
  },
  {
    "id": "v_3d8be866",
    "word": "Carnations",
    "translation": "clavel",
    "source_movie": "Taylor Swift The Eras Tour Film",
    "year_processed": "2024",
    "global_frequency": 2
  }
]